{
"meta":{"test_sets":[],"test_metrics":[],"learn_metrics":[{"best_value":"Min","name":"Logloss"}],"launch_mode":"Train","parameters":"","iteration_count":1000,"learn_sets":["learn"],"name":"experiment"},
"iterations":[
{"learn":[0.6882071534],"iteration":0,"passed_time":0.001312710379,"remaining_time":1.311397669},
{"learn":[0.6836531989],"iteration":1,"passed_time":0.00273566163,"remaining_time":1.365095153},
{"learn":[0.6785761393],"iteration":2,"passed_time":0.004039001935,"remaining_time":1.342294976},
{"learn":[0.6743400797],"iteration":3,"passed_time":0.00525127152,"remaining_time":1.307566609},
{"learn":[0.6692562894],"iteration":4,"passed_time":0.006437960903,"remaining_time":1.28115422},
{"learn":[0.6648209522],"iteration":5,"passed_time":0.007800791679,"remaining_time":1.292331155},
{"learn":[0.6601736294],"iteration":6,"passed_time":0.008672088568,"remaining_time":1.230197707},
{"learn":[0.6562772967],"iteration":7,"passed_time":0.009723926884,"remaining_time":1.205766934},
{"learn":[0.6515273871],"iteration":8,"passed_time":0.01091172628,"remaining_time":1.201502304},
{"learn":[0.6470511202],"iteration":9,"passed_time":0.01178827321,"remaining_time":1.167039047},
{"learn":[0.643363847],"iteration":10,"passed_time":0.01263769992,"remaining_time":1.136244111},
{"learn":[0.6393272442],"iteration":11,"passed_time":0.01351493686,"remaining_time":1.112729801},
{"learn":[0.6356606554],"iteration":12,"passed_time":0.01439948385,"remaining_time":1.09325312},
{"learn":[0.6311109751],"iteration":13,"passed_time":0.01598319637,"remaining_time":1.125673688},
{"learn":[0.6275209007],"iteration":14,"passed_time":0.01765709961,"remaining_time":1.159482874},
{"learn":[0.6233397728],"iteration":15,"passed_time":0.01849808626,"remaining_time":1.137632305},
{"learn":[0.6196865231],"iteration":16,"passed_time":0.01929594257,"remaining_time":1.115759503},
{"learn":[0.615802254],"iteration":17,"passed_time":0.0201227591,"remaining_time":1.097808302},
{"learn":[0.6120622662],"iteration":18,"passed_time":0.02092318543,"remaining_time":1.080297101},
{"learn":[0.6080722779],"iteration":19,"passed_time":0.02169362152,"remaining_time":1.062987455},
{"learn":[0.6043351753],"iteration":20,"passed_time":0.02247221768,"remaining_time":1.047633386},
{"learn":[0.6006139787],"iteration":21,"passed_time":0.02323733373,"remaining_time":1.033005109},
{"learn":[0.5975940248],"iteration":22,"passed_time":0.02400397979,"remaining_time":1.019647316},
{"learn":[0.5946410692],"iteration":23,"passed_time":0.02488250674,"remaining_time":1.011888607},
{"learn":[0.5908152582],"iteration":24,"passed_time":0.02586256449,"remaining_time":1.008640015},
{"learn":[0.587906862],"iteration":25,"passed_time":0.02668443099,"remaining_time":0.9996398377},
{"learn":[0.5847566307],"iteration":26,"passed_time":0.02748065728,"remaining_time":0.9903214642},
{"learn":[0.5814817728],"iteration":27,"passed_time":0.02837427435,"remaining_time":0.9849926666},
{"learn":[0.5786010236],"iteration":28,"passed_time":0.02918843078,"remaining_time":0.9773091825},
{"learn":[0.5753846298],"iteration":29,"passed_time":0.02995489684,"remaining_time":0.9685416646},
{"learn":[0.5723816451],"iteration":30,"passed_time":0.03123269695,"remaining_time":0.9762736562},
{"learn":[0.5693658701],"iteration":31,"passed_time":0.03209803379,"remaining_time":0.9709655221},
{"learn":[0.5669382116],"iteration":32,"passed_time":0.03295620057,"remaining_time":0.9657165441},
{"learn":[0.564059628],"iteration":33,"passed_time":0.03376801699,"remaining_time":0.9594089534},
{"learn":[0.5614069887],"iteration":34,"passed_time":0.03465341399,"remaining_time":0.9554441287},
{"learn":[0.5590774298],"iteration":35,"passed_time":0.03554285103,"remaining_time":0.9517585664},
{"learn":[0.556222289],"iteration":36,"passed_time":0.03632079718,"remaining_time":0.9453223698},
{"learn":[0.55371845],"iteration":37,"passed_time":0.03711612347,"remaining_time":0.9396239677},
{"learn":[0.5505935561],"iteration":38,"passed_time":0.03791605979,"remaining_time":0.9342906015},
{"learn":[0.5483602787],"iteration":39,"passed_time":0.03874286633,"remaining_time":0.9298287919},
{"learn":[0.5459297896],"iteration":40,"passed_time":0.03957777293,"remaining_time":0.9257337619},
{"learn":[0.5436040044],"iteration":41,"passed_time":0.04039169937,"remaining_time":0.9213154284},
{"learn":[0.5416563618],"iteration":42,"passed_time":0.04130319657,"remaining_time":0.9192362586},
{"learn":[0.5391108746],"iteration":43,"passed_time":0.04206092256,"remaining_time":0.9138691357},
{"learn":[0.536701945],"iteration":44,"passed_time":0.04279310835,"remaining_time":0.908164855},
{"learn":[0.5340843341],"iteration":45,"passed_time":0.04350508398,"remaining_time":0.9022576113},
{"learn":[0.5322203928],"iteration":46,"passed_time":0.04421770962,"remaining_time":0.8965846226},
{"learn":[0.5305816065],"iteration":47,"passed_time":0.04495748547,"remaining_time":0.8916567951},
{"learn":[0.5282018819],"iteration":48,"passed_time":0.04630633613,"remaining_time":0.8987209318},
{"learn":[0.5262117526],"iteration":49,"passed_time":0.04706767215,"remaining_time":0.8942857709},
{"learn":[0.5242086253],"iteration":50,"passed_time":0.04791890888,"remaining_time":0.8916675398},
{"learn":[0.5222547195],"iteration":51,"passed_time":0.04868367493,"remaining_time":0.8875408429},
{"learn":[0.520504879],"iteration":52,"passed_time":0.04941112068,"remaining_time":0.8828741752},
{"learn":[0.5183396797],"iteration":53,"passed_time":0.05015554656,"remaining_time":0.8786508713},
{"learn":[0.5166059637],"iteration":54,"passed_time":0.05090418248,"remaining_time":0.8746264081},
{"learn":[0.5140312827],"iteration":55,"passed_time":0.05162535819,"remaining_time":0.870256038},
{"learn":[0.5119178681],"iteration":56,"passed_time":0.05239268425,"remaining_time":0.8667772149},
{"learn":[0.5101345289],"iteration":57,"passed_time":0.05326452115,"remaining_time":0.8650892917},
{"learn":[0.508344793],"iteration":58,"passed_time":0.0540551574,"remaining_time":0.862133951},
{"learn":[0.5062081291],"iteration":59,"passed_time":0.05487091385,"remaining_time":0.859644317},
{"learn":[0.5042694118],"iteration":60,"passed_time":0.05566744015,"remaining_time":0.8569135459},
{"learn":[0.5026237427],"iteration":61,"passed_time":0.05647840656,"remaining_time":0.8544636347},
{"learn":[0.5007872497],"iteration":62,"passed_time":0.05731682319,"remaining_time":0.8524740211},
{"learn":[0.4986874036],"iteration":63,"passed_time":0.05935041927,"remaining_time":0.8679998818},
{"learn":[0.4969056383],"iteration":64,"passed_time":0.06017059575,"remaining_time":0.8655308773},
{"learn":[0.4947956353],"iteration":65,"passed_time":0.06089208146,"remaining_time":0.8617152133},
{"learn":[0.4926085442],"iteration":66,"passed_time":0.06162247723,"remaining_time":0.8581159889},
{"learn":[0.4906713456],"iteration":67,"passed_time":0.06376426416,"remaining_time":0.873945503},
{"learn":[0.4892952575],"iteration":68,"passed_time":0.06455968045,"remaining_time":0.8710878624},
{"learn":[0.487628841],"iteration":69,"passed_time":0.06532024647,"remaining_time":0.8678261316},
{"learn":[0.4859113729],"iteration":70,"passed_time":0.06608512252,"remaining_time":0.8646912509},
{"learn":[0.4840497417],"iteration":71,"passed_time":0.06683300843,"remaining_time":0.8614032197},
{"learn":[0.4826651405],"iteration":72,"passed_time":0.06758710439,"remaining_time":0.8582636407},
{"learn":[0.4809617416],"iteration":73,"passed_time":0.06832610023,"remaining_time":0.8549995786},
{"learn":[0.4794498361],"iteration":74,"passed_time":0.06912956659,"remaining_time":0.8525979879},
{"learn":[0.4776751249],"iteration":75,"passed_time":0.06987905251,"remaining_time":0.8495821648},
{"learn":[0.4764146406],"iteration":76,"passed_time":0.07108276203,"remaining_time":0.8520699916},
{"learn":[0.4753679967],"iteration":77,"passed_time":0.07189957849,"remaining_time":0.8498898893},
{"learn":[0.47402234],"iteration":78,"passed_time":0.07296698693,"remaining_time":0.850665759},
{"learn":[0.4727231567],"iteration":79,"passed_time":0.07375355315,"remaining_time":0.8481658612},
{"learn":[0.4713849257],"iteration":80,"passed_time":0.07460201986,"remaining_time":0.846410571},
{"learn":[0.4697723701],"iteration":81,"passed_time":0.0753669759,"remaining_time":0.8437424863},
{"learn":[0.4683651312],"iteration":82,"passed_time":0.0761505421,"remaining_time":0.8413258687},
{"learn":[0.466727857],"iteration":83,"passed_time":0.07687457782,"remaining_time":0.8382989677},
{"learn":[0.4654716671],"iteration":84,"passed_time":0.07799855671,"remaining_time":0.8396315222},
{"learn":[0.4638928268],"iteration":85,"passed_time":0.07872034242,"remaining_time":0.8366324764},
{"learn":[0.4626103994],"iteration":86,"passed_time":0.07872034242,"remaining_time":0.8366324764},
{"learn":[0.4612708999],"iteration":87,"passed_time":0.09891007205,"remaining_time":1.03685041},
{"learn":[0.46004762],"iteration":88,"passed_time":0.1002634228,"remaining_time":1.037954297},
{"learn":[0.4585454607],"iteration":89,"passed_time":0.101681134,"remaining_time":1.039661033},
{"learn":[0.4577015592],"iteration":90,"passed_time":0.1030589749,"remaining_time":1.040895646},
{"learn":[0.4567401093],"iteration":91,"passed_time":0.104218294,"remaining_time":1.039892428},
{"learn":[0.4558828864],"iteration":92,"passed_time":0.1054016434,"remaining_time":1.039122723},
{"learn":[0.4548140414],"iteration":93,"passed_time":0.1062573501,"remaining_time":1.03515225},
{"learn":[0.4536194603],"iteration":94,"passed_time":0.1070336663,"remaining_time":1.030483702},
{"learn":[0.452594213],"iteration":95,"passed_time":0.1078457527,"remaining_time":1.026237478},
{"learn":[0.4510977537],"iteration":96,"passed_time":0.1086279289,"remaining_time":1.021781456},
{"learn":[0.449892611],"iteration":97,"passed_time":0.1094179451,"remaining_time":1.017474088},
{"learn":[0.4486165421],"iteration":98,"passed_time":0.1103458525,"remaining_time":1.014506256},
{"learn":[0.4476744821],"iteration":99,"passed_time":0.111040098,"remaining_time":1.009455436},
{"learn":[0.4468130794],"iteration":100,"passed_time":0.1117221334,"remaining_time":1.004381979},
{"learn":[0.4461396722],"iteration":101,"passed_time":0.1124673992,"remaining_time":0.9999576685},
{"learn":[0.4447767934],"iteration":102,"passed_time":0.1131722948,"remaining_time":0.995250475},
{"learn":[0.4440830381],"iteration":103,"passed_time":0.1138575702,"remaining_time":0.9904503197},
{"learn":[0.4428951576],"iteration":104,"passed_time":0.1145337956,"remaining_time":0.9856514139},
{"learn":[0.4419327653],"iteration":105,"passed_time":0.1152004409,"remaining_time":0.9808494679},
{"learn":[0.4409417701],"iteration":106,"passed_time":0.1158827162,"remaining_time":0.9762572227},
{"learn":[0.4399902977],"iteration":107,"passed_time":0.1165752917,"remaining_time":0.9718239273},
{"learn":[0.4388918373],"iteration":108,"passed_time":0.1172852273,"remaining_time":0.9676031255},
{"learn":[0.4379589031],"iteration":109,"passed_time":0.1180190031,"remaining_time":0.9636414018},
{"learn":[0.4370252036],"iteration":110,"passed_time":0.1187113086,"remaining_time":0.9594032124},
{"learn":[0.4359287347],"iteration":111,"passed_time":0.1194715346,"remaining_time":0.955772277},
{"learn":[0.4348346524],"iteration":112,"passed_time":0.1201733002,"remaining_time":0.9517296183},
{"learn":[0.4341203397],"iteration":113,"passed_time":0.1208727757,"remaining_time":0.9477281352},
{"learn":[0.4331897474],"iteration":114,"passed_time":0.1215616812,"remaining_time":0.9437025247},
{"learn":[0.432105529],"iteration":115,"passed_time":0.1222327365,"remaining_time":0.9395977307},
{"learn":[0.4315861779],"iteration":116,"passed_time":0.1229269119,"remaining_time":0.9357281315},
{"learn":[0.4304127087],"iteration":117,"passed_time":0.1236386076,"remaining_time":0.9320448879},
{"learn":[0.4297652916],"iteration":118,"passed_time":0.1243132729,"remaining_time":0.9281355376},
{"learn":[0.4288075711],"iteration":119,"passed_time":0.1250019584,"remaining_time":0.9243842298},
{"learn":[0.4279404239],"iteration":120,"passed_time":0.125721654,"remaining_time":0.9209111159},
{"learn":[0.4271267981],"iteration":121,"passed_time":0.1264634799,"remaining_time":0.9176440939},
{"learn":[0.4263140736],"iteration":122,"passed_time":0.1272698263,"remaining_time":0.9148822758},
{"learn":[0.4254453763],"iteration":123,"passed_time":0.1279638418,"remaining_time":0.911352239},
{"learn":[0.4246368709],"iteration":124,"passed_time":0.128876189,"remaining_time":0.9094085916},
{"learn":[0.4239310883],"iteration":125,"passed_time":0.1295496243,"remaining_time":0.9058109732},
{"learn":[0.4233831931],"iteration":126,"passed_time":0.1302607999,"remaining_time":0.9025212567},
{"learn":[0.4227985471],"iteration":127,"passed_time":0.1309452953,"remaining_time":0.899088957},
{"learn":[0.4220171674],"iteration":128,"passed_time":0.1316351008,"remaining_time":0.895735725},
{"learn":[0.4213693523],"iteration":129,"passed_time":0.1323139062,"remaining_time":0.8923495997},
{"learn":[0.4205342889],"iteration":130,"passed_time":0.1330106617,"remaining_time":0.8891251154},
{"learn":[0.4196128205],"iteration":131,"passed_time":0.1338288381,"remaining_time":0.886743752},
{"learn":[0.4186842859],"iteration":132,"passed_time":0.1345234636,"remaining_time":0.883574568},
{"learn":[0.4179180232],"iteration":133,"passed_time":0.1352405193,"remaining_time":0.8805886445},
{"learn":[0.4171581443],"iteration":134,"passed_time":0.1359143746,"remaining_time":0.8773577169},
{"learn":[0.4162892013],"iteration":135,"passed_time":0.13659664,"remaining_time":0.8742184962},
{"learn":[0.4156767486],"iteration":136,"passed_time":0.1372951756,"remaining_time":0.8712186507},
{"learn":[0.4150169144],"iteration":137,"passed_time":0.1379907011,"remaining_time":0.8682334621},
{"learn":[0.4144992993],"iteration":138,"passed_time":0.1390668896,"remaining_time":0.8676564631},
{"learn":[0.4137695855],"iteration":139,"passed_time":0.1397620051,"remaining_time":0.8647145637},
{"learn":[0.4132092798],"iteration":140,"passed_time":0.1404600006,"remaining_time":0.8618224321},
{"learn":[0.4124491241],"iteration":141,"passed_time":0.1411594161,"remaining_time":0.858970064},
{"learn":[0.4118890503],"iteration":142,"passed_time":0.1418429815,"remaining_time":0.8560523602},
{"learn":[0.4110728966],"iteration":143,"passed_time":0.1425452771,"remaining_time":0.8532780221},
{"learn":[0.4107126712],"iteration":144,"passed_time":0.1432450426,"remaining_time":0.8505174404},
{"learn":[0.4098386204],"iteration":145,"passed_time":0.1439508482,"remaining_time":0.8478208575},
{"learn":[0.4090916212],"iteration":146,"passed_time":0.1446541737,"remaining_time":0.8451370562},
{"learn":[0.4085802962],"iteration":147,"passed_time":0.1453452692,"remaining_time":0.8424093154},
{"learn":[0.4080448161],"iteration":148,"passed_time":0.1460620649,"remaining_time":0.839856873},
{"learn":[0.4073943849],"iteration":149,"passed_time":0.1467759205,"remaining_time":0.8373122982},
{"learn":[0.4068776518],"iteration":150,"passed_time":0.1476428874,"remaining_time":0.8356587425},
{"learn":[0.4060092246],"iteration":151,"passed_time":0.1483643631,"remaining_time":0.8331985423},
{"learn":[0.4052365521],"iteration":152,"passed_time":0.1491811695,"remaining_time":0.8312924381},
{"learn":[0.4045739347],"iteration":153,"passed_time":0.1498555549,"remaining_time":0.8286130681},
{"learn":[0.4039899258],"iteration":154,"passed_time":0.1505433203,"remaining_time":0.8260331536},
{"learn":[0.4036847347],"iteration":155,"passed_time":0.1512159956,"remaining_time":0.8233954858},
{"learn":[0.4030753959],"iteration":156,"passed_time":0.1519297113,"remaining_time":0.8210047859},
{"learn":[0.4022757174],"iteration":157,"passed_time":0.1526659171,"remaining_time":0.8187560649},
{"learn":[0.4020858537],"iteration":158,"passed_time":0.1533736227,"remaining_time":0.8163747891},
{"learn":[0.4015108159],"iteration":159,"passed_time":0.1540317979,"remaining_time":0.8137528945},
{"learn":[0.400978047],"iteration":160,"passed_time":0.1547034832,"remaining_time":0.81122639},
{"learn":[0.4001797511],"iteration":161,"passed_time":0.1553849786,"remaining_time":0.8087739879},
{"learn":[0.3995690914],"iteration":162,"passed_time":0.1561901449,"remaining_time":0.8069824156},
{"learn":[0.3992112757],"iteration":163,"passed_time":0.1568603902,"remaining_time":0.8045109586},
{"learn":[0.3985712165],"iteration":164,"passed_time":0.1576197163,"remaining_time":0.8025150187},
{"learn":[0.3979769546],"iteration":165,"passed_time":0.1582954216,"remaining_time":0.8001114037},
{"learn":[0.3977121212],"iteration":166,"passed_time":0.1590138873,"remaining_time":0.7979431813},
{"learn":[0.3973017418],"iteration":167,"passed_time":0.1596951527,"remaining_time":0.7956069881},
{"learn":[0.3969902396],"iteration":168,"passed_time":0.1604205084,"remaining_time":0.7935085862},
{"learn":[0.3964683136],"iteration":169,"passed_time":0.1611675043,"remaining_time":0.7915327134},
{"learn":[0.3961169432],"iteration":170,"passed_time":0.1618610498,"remaining_time":0.7893106487},
{"learn":[0.3954530218],"iteration":171,"passed_time":0.1625539753,"remaining_time":0.7871034592},
{"learn":[0.3950176707],"iteration":172,"passed_time":0.1633840918,"remaining_time":0.7855735113},
{"learn":[0.3945667598],"iteration":173,"passed_time":0.1641101476,"remaining_time":0.7835548086},
{"learn":[0.3942973489],"iteration":174,"passed_time":0.1649513442,"remaining_time":0.7820968907},
{"learn":[0.3937935782],"iteration":175,"passed_time":0.1656746099,"remaining_time":0.7800907348},
{"learn":[0.3932932647],"iteration":176,"passed_time":0.1663760655,"remaining_time":0.7779971699},
{"learn":[0.3926952208],"iteration":177,"passed_time":0.1670457308,"remaining_time":0.7757716989},
{"learn":[0.3920891159],"iteration":178,"passed_time":0.1677355362,"remaining_time":0.7736566025},
{"learn":[0.391563206],"iteration":179,"passed_time":0.168463402,"remaining_time":0.7717317857},
{"learn":[0.3910815194],"iteration":180,"passed_time":0.1691522474,"remaining_time":0.7696427258},
{"learn":[0.3906998537],"iteration":181,"passed_time":0.1698342628,"remaining_time":0.7675382707},
{"learn":[0.3901933137],"iteration":182,"passed_time":0.1705454585,"remaining_time":0.7655804371},
{"learn":[0.3898301406],"iteration":183,"passed_time":0.1712294639,"remaining_time":0.7635149864},
{"learn":[0.3892359393],"iteration":184,"passed_time":0.1719263294,"remaining_time":0.7615215132},
{"learn":[0.3888616772],"iteration":185,"passed_time":0.1726116348,"remaining_time":0.7594911931},
{"learn":[0.3884303187],"iteration":186,"passed_time":0.1733075303,"remaining_time":0.7575216243},
{"learn":[0.3880278237],"iteration":187,"passed_time":0.1739963557,"remaining_time":0.7555349779},
{"learn":[0.3872070271],"iteration":188,"passed_time":0.1747119414,"remaining_time":0.753677577},
{"learn":[0.3866664146],"iteration":189,"passed_time":0.1756036284,"remaining_time":0.7525869791},
{"learn":[0.3863785397],"iteration":190,"passed_time":0.1766993171,"remaining_time":0.7523670923},
{"learn":[0.3858047715],"iteration":191,"passed_time":0.177444703,"remaining_time":0.7506561258},
{"learn":[0.3853670792],"iteration":192,"passed_time":0.1783070898,"remaining_time":0.7494469869},
{"learn":[0.385046969],"iteration":193,"passed_time":0.1790150754,"remaining_time":0.7475966362},
{"learn":[0.3844672762],"iteration":194,"passed_time":0.1797374111,"remaining_time":0.745817608},
{"learn":[0.3841599882],"iteration":195,"passed_time":0.1805144273,"remaining_time":0.7442748694},
{"learn":[0.3839052321],"iteration":196,"passed_time":0.1812072528,"remaining_time":0.7423950202},
{"learn":[0.3835404273],"iteration":197,"passed_time":0.181992279,"remaining_time":0.7409025773},
{"learn":[0.3831886912],"iteration":198,"passed_time":0.1827468649,"remaining_time":0.7392941354},
{"learn":[0.3827806185],"iteration":199,"passed_time":0.1835563713,"remaining_time":0.7379150606},
{"learn":[0.3824763244],"iteration":200,"passed_time":0.1843558676,"remaining_time":0.7365016912},
{"learn":[0.3820073399],"iteration":201,"passed_time":0.1851269637,"remaining_time":0.734981677},
{"learn":[0.3814807165],"iteration":202,"passed_time":0.1859660204,"remaining_time":0.733737219},
{"learn":[0.381216993],"iteration":203,"passed_time":0.1869126779,"remaining_time":0.7329186777},
{"learn":[0.3808290646],"iteration":204,"passed_time":0.1885965212,"remaining_time":0.7349717369},
{"learn":[0.380544937],"iteration":205,"passed_time":0.1898085608,"remaining_time":0.7351609622},
{"learn":[0.3801411257],"iteration":206,"passed_time":0.1912068318,"remaining_time":0.7360534836},
{"learn":[0.3797310388],"iteration":207,"passed_time":0.1927036637,"remaining_time":0.737300974},
{"learn":[0.3794240215],"iteration":208,"passed_time":0.1939112632,"remaining_time":0.7374221596},
{"learn":[0.379036961],"iteration":209,"passed_time":0.195532846,"remaining_time":0.7390954467},
{"learn":[0.3785219639],"iteration":210,"passed_time":0.1963827727,"remaining_time":0.7378381319},
{"learn":[0.3782984091],"iteration":211,"passed_time":0.1973623405,"remaining_time":0.7370688356},
{"learn":[0.3777491729],"iteration":212,"passed_time":0.1985303197,"remaining_time":0.7369969888},
{"learn":[0.3774315435],"iteration":213,"passed_time":0.1999646311,"remaining_time":0.7378976526},
{"learn":[0.377071639],"iteration":214,"passed_time":0.2008216478,"remaining_time":0.7366588484},
{"learn":[0.376508428],"iteration":215,"passed_time":0.2016475044,"remaining_time":0.7353099694},
{"learn":[0.3760721129],"iteration":216,"passed_time":0.202482261,"remaining_time":0.733998196},
{"learn":[0.3755347194],"iteration":217,"passed_time":0.2035755696,"remaining_time":0.7336225596},
{"learn":[0.3751071101],"iteration":218,"passed_time":0.2047941492,"remaining_time":0.733689131},
{"learn":[0.3748061407],"iteration":219,"passed_time":0.2066168137,"remaining_time":0.7358955007},
{"learn":[0.3745182886],"iteration":220,"passed_time":0.2075754012,"remaining_time":0.7350056253},
{"learn":[0.3738992048],"iteration":221,"passed_time":0.208806081,"remaining_time":0.7350729909},
{"learn":[0.3736551219],"iteration":222,"passed_time":0.2102715526,"remaining_time":0.7359504339},
{"learn":[0.3733448156],"iteration":223,"passed_time":0.2117918646,"remaining_time":0.7369976991},
{"learn":[0.3727578936],"iteration":224,"passed_time":0.213116215,"remaining_time":0.7373440476},
{"learn":[0.3721752101],"iteration":225,"passed_time":0.2146043568,"remaining_time":0.7382389874},
{"learn":[0.3718847858],"iteration":226,"passed_time":0.2159149072,"remaining_time":0.7385054126},
{"learn":[0.3715193987],"iteration":227,"passed_time":0.2172321676,"remaining_time":0.7387807638},
{"learn":[0.3712236418],"iteration":228,"passed_time":0.2187911899,"remaining_time":0.7398596817},
{"learn":[0.3707383271],"iteration":229,"passed_time":0.2198798085,"remaining_time":0.739333854},
{"learn":[0.3704245213],"iteration":230,"passed_time":0.2209672871,"remaining_time":0.7387993209},
{"learn":[0.3700524299],"iteration":231,"passed_time":0.2218971045,"remaining_time":0.7377358279},
{"learn":[0.3696491955],"iteration":232,"passed_time":0.2229446428,"remaining_time":0.7370626767},
{"learn":[0.3691493483],"iteration":233,"passed_time":0.2238445799,"remaining_time":0.7359010652},
{"learn":[0.3688057467],"iteration":234,"passed_time":0.2245196952,"remaining_time":0.7340066959},
{"learn":[0.3684494035],"iteration":235,"passed_time":0.225249281,"remaining_time":0.7322997901},
{"learn":[0.3681161629],"iteration":236,"passed_time":0.2259960669,"remaining_time":0.7306567756},
{"learn":[0.3678318547],"iteration":237,"passed_time":0.2267051125,"remaining_time":0.7288999819},
{"learn":[0.3677046951],"iteration":238,"passed_time":0.2274735786,"remaining_time":0.7273419886},
{"learn":[0.3673524681],"iteration":239,"passed_time":0.2281796041,"remaining_time":0.7255920467},
{"learn":[0.3670323964],"iteration":240,"passed_time":0.2288680496,"remaining_time":0.7237952068},
{"learn":[0.3667652124],"iteration":241,"passed_time":0.2295662751,"remaining_time":0.7220383259},
{"learn":[0.3664114522],"iteration":242,"passed_time":0.2302521005,"remaining_time":0.7202514054},
{"learn":[0.3660964752],"iteration":243,"passed_time":0.2309346659,"remaining_time":0.7184634051},
{"learn":[0.3658659409],"iteration":244,"passed_time":0.2316213114,"remaining_time":0.7166970905},
{"learn":[0.3654961015],"iteration":245,"passed_time":0.2322765965,"remaining_time":0.7148430767},
{"learn":[0.3651765481],"iteration":246,"passed_time":0.2330378826,"remaining_time":0.7133232747},
{"learn":[0.3648938777],"iteration":247,"passed_time":0.2337192879,"remaining_time":0.7115664151},
{"learn":[0.3646417213],"iteration":248,"passed_time":0.234353243,"remaining_time":0.7096745382},
{"learn":[0.3642380789],"iteration":249,"passed_time":0.2350655286,"remaining_time":0.7080287006},
{"learn":[0.3639928814],"iteration":250,"passed_time":0.235755674,"remaining_time":0.7063239995},
{"learn":[0.3636998146],"iteration":251,"passed_time":0.2364799398,"remaining_time":0.7047290636},
{"learn":[0.3634017417],"iteration":252,"passed_time":0.2371865854,"remaining_time":0.7030888066},
{"learn":[0.3630628033],"iteration":253,"passed_time":0.2378869809,"remaining_time":0.701437501},
{"learn":[0.362619825],"iteration":254,"passed_time":0.2385713463,"remaining_time":0.6997466654},
{"learn":[0.3624169516],"iteration":255,"passed_time":0.2392553417,"remaining_time":0.6980626441},
{"learn":[0.3620703866],"iteration":256,"passed_time":0.2399422072,"remaining_time":0.6963947653},
{"learn":[0.3617068104],"iteration":257,"passed_time":0.2407513235,"remaining_time":0.6950874789},
{"learn":[0.3613782987],"iteration":258,"passed_time":0.2415973302,"remaining_time":0.6938900066},
{"learn":[0.3611099577],"iteration":259,"passed_time":0.2422868457,"remaining_time":0.6922481305},
{"learn":[0.3607711503],"iteration":260,"passed_time":0.2430567018,"remaining_time":0.6908419331},
{"learn":[0.3605449775],"iteration":261,"passed_time":0.2437469072,"remaining_time":0.6892153929},
{"learn":[0.3602590125],"iteration":262,"passed_time":0.2444148825,"remaining_time":0.6875334672},
{"learn":[0.3600112866],"iteration":263,"passed_time":0.245107948,"remaining_time":0.6859294666},
{"learn":[0.3597725458],"iteration":264,"passed_time":0.2457678932,"remaining_time":0.6842401572},
{"learn":[0.3595558243],"iteration":265,"passed_time":0.2464545386,"remaining_time":0.6826325712},
{"learn":[0.3591995575],"iteration":266,"passed_time":0.2471390741,"remaining_time":0.681026095},
{"learn":[0.3589970845],"iteration":267,"passed_time":0.2479482705,"remaining_time":0.679768292},
{"learn":[0.3587129233],"iteration":268,"passed_time":0.2486789262,"remaining_time":0.6782996085},
{"learn":[0.3583231576],"iteration":269,"passed_time":0.249405962,"remaining_time":0.6768265883},
{"learn":[0.35807439],"iteration":270,"passed_time":0.2500934974,"remaining_time":0.675252443},
{"learn":[0.3578457704],"iteration":271,"passed_time":0.2508955638,"remaining_time":0.6739925108},
{"learn":[0.3575657849],"iteration":272,"passed_time":0.2517004201,"remaining_time":0.6727434023},
{"learn":[0.3570884827],"iteration":273,"passed_time":0.2524303559,"remaining_time":0.6712983091},
{"learn":[0.3567367657],"iteration":274,"passed_time":0.253200402,"remaining_time":0.6699645673},
{"learn":[0.3565107934],"iteration":275,"passed_time":0.2540140384,"remaining_time":0.6687496866},
{"learn":[0.356166969],"iteration":276,"passed_time":0.2548032747,"remaining_time":0.6674737956},
{"learn":[0.3558330911],"iteration":277,"passed_time":0.2555582006,"remaining_time":0.6661119886},
{"learn":[0.3555912733],"iteration":278,"passed_time":0.2563207567,"remaining_time":0.6647743365},
{"learn":[0.3553356321],"iteration":279,"passed_time":0.2570980028,"remaining_time":0.6634787169},
{"learn":[0.3550709781],"iteration":280,"passed_time":0.2579077492,"remaining_time":0.662270256},
{"learn":[0.3547238005],"iteration":281,"passed_time":0.2586799653,"remaining_time":0.660968737},
{"learn":[0.3543683348],"iteration":282,"passed_time":0.2594473814,"remaining_time":0.6596587675},
{"learn":[0.3541757294],"iteration":283,"passed_time":0.2602652878,"remaining_time":0.6584803749},
{"learn":[0.3537166785],"iteration":284,"passed_time":0.2610139438,"remaining_time":0.6571301753},
{"learn":[0.3533615658],"iteration":285,"passed_time":0.2617795398,"remaining_time":0.6558266366},
{"learn":[0.3531720154],"iteration":286,"passed_time":0.2625731861,"remaining_time":0.6545967891},
{"learn":[0.3529410019],"iteration":287,"passed_time":0.263319982,"remaining_time":0.6532537532},
{"learn":[0.3524990854],"iteration":288,"passed_time":0.2640705379,"remaining_time":0.6519241405},
{"learn":[0.3521064718],"iteration":289,"passed_time":0.2648657342,"remaining_time":0.6507082052},
{"learn":[0.3518364706],"iteration":290,"passed_time":0.2656364903,"remaining_time":0.6494354194},
{"learn":[0.3514340108],"iteration":291,"passed_time":0.2664189465,"remaining_time":0.6481945502},
{"learn":[0.3509728496],"iteration":292,"passed_time":0.2671611324,"remaining_time":0.6468593171},
{"learn":[0.3508510068],"iteration":293,"passed_time":0.2677282968,"remaining_time":0.6451064081},
{"learn":[0.3505389334],"iteration":294,"passed_time":0.2684843228,"remaining_time":0.6438144476},
{"learn":[0.3500907449],"iteration":295,"passed_time":0.269264539,"remaining_time":0.642583849},
{"learn":[0.3496980862],"iteration":296,"passed_time":0.270028585,"remaining_time":0.6413178895},
{"learn":[0.3494129233],"iteration":297,"passed_time":0.2707740909,"remaining_time":0.6400114877},
{"learn":[0.3491322505],"iteration":298,"passed_time":0.271546037,"remaining_time":0.6387710468},
{"learn":[0.3487454121],"iteration":299,"passed_time":0.2728905577,"remaining_time":0.6388742153},
{"learn":[0.3485891898],"iteration":300,"passed_time":0.2773083626,"remaining_time":0.6461284848},
{"learn":[0.3483659591],"iteration":301,"passed_time":0.2782006296,"remaining_time":0.6451296993},
{"learn":[0.3479791069],"iteration":302,"passed_time":0.2790682965,"remaining_time":0.6440748433},
{"learn":[0.3477066749],"iteration":303,"passed_time":0.2799444634,"remaining_time":0.6430407477},
{"learn":[0.3474224141],"iteration":304,"passed_time":0.28076842,"remaining_time":0.6418883285},
{"learn":[0.3472901722],"iteration":305,"passed_time":0.2817078474,"remaining_time":0.6410008068},
{"learn":[0.3470994383],"iteration":306,"passed_time":0.282540704,"remaining_time":0.6398715943},
{"learn":[0.3469719295],"iteration":307,"passed_time":0.2834235509,"remaining_time":0.6388569943},
{"learn":[0.3467368041],"iteration":308,"passed_time":0.2842463075,"remaining_time":0.6377084365},
{"learn":[0.3464151809],"iteration":309,"passed_time":0.2850346637,"remaining_time":0.6364851713},
{"learn":[0.3461777358],"iteration":310,"passed_time":0.2858704303,"remaining_time":0.6353700854},
{"learn":[0.3459212515],"iteration":311,"passed_time":0.2866633566,"remaining_time":0.6341620235},
{"learn":[0.345621191],"iteration":312,"passed_time":0.2874566228,"remaining_time":0.6329573714},
{"learn":[0.3455315416],"iteration":313,"passed_time":0.2883149696,"remaining_time":0.6318979845},
{"learn":[0.3452451801],"iteration":314,"passed_time":0.2891457862,"remaining_time":0.6307798202},
{"learn":[0.3449823725],"iteration":315,"passed_time":0.2902793052,"remaining_time":0.6303207769},
{"learn":[0.3445873252],"iteration":316,"passed_time":0.2910285211,"remaining_time":0.6290268351},
{"learn":[0.3443183967],"iteration":317,"passed_time":0.2917928871,"remaining_time":0.6277689243},
{"learn":[0.3439892677],"iteration":318,"passed_time":0.292532643,"remaining_time":0.6264614147},
{"learn":[0.3437147626],"iteration":319,"passed_time":0.2932681988,"remaining_time":0.6251485115},
{"learn":[0.34352229],"iteration":320,"passed_time":0.2939998746,"remaining_time":0.6238309839},
{"learn":[0.3432463218],"iteration":321,"passed_time":0.2947650706,"remaining_time":0.6225879062},
{"learn":[0.3429097947],"iteration":322,"passed_time":0.2954737962,"remaining_time":0.6212290685},
{"learn":[0.3425956144],"iteration":323,"passed_time":0.296203342,"remaining_time":0.6199178303},
{"learn":[0.3423473763],"iteration":324,"passed_time":0.2969382878,"remaining_time":0.6186214329},
{"learn":[0.3420882842],"iteration":325,"passed_time":0.2976479134,"remaining_time":0.6172759804},
{"learn":[0.3417604582],"iteration":326,"passed_time":0.2984019094,"remaining_time":0.6160260276},
{"learn":[0.3414773622],"iteration":327,"passed_time":0.2991459553,"remaining_time":0.6147586603},
{"learn":[0.3414032425],"iteration":328,"passed_time":0.299868451,"remaining_time":0.6134503982},
{"learn":[0.3409348173],"iteration":329,"passed_time":0.300632607,"remaining_time":0.6122305371},
{"learn":[0.3405469348],"iteration":330,"passed_time":0.301393323,"remaining_time":0.611006464},
{"learn":[0.3403039984],"iteration":331,"passed_time":0.3021593091,"remaining_time":0.6097958262},
{"learn":[0.3400831496],"iteration":332,"passed_time":0.3028893749,"remaining_time":0.6085157019},
{"learn":[0.339855984],"iteration":333,"passed_time":0.3036091405,"remaining_time":0.6072182811},
{"learn":[0.3394614372],"iteration":334,"passed_time":0.3043759866,"remaining_time":0.6060180572},
{"learn":[0.3390406965],"iteration":335,"passed_time":0.3051005923,"remaining_time":0.6047366965},
{"learn":[0.3386688151],"iteration":336,"passed_time":0.3059667292,"remaining_time":0.603737921},
{"learn":[0.3384003543],"iteration":337,"passed_time":0.3067099551,"remaining_time":0.6024984874},
{"learn":[0.338120328],"iteration":338,"passed_time":0.3074307908,"remaining_time":0.6012182032},
{"learn":[0.3379346936],"iteration":339,"passed_time":0.3081762667,"remaining_time":0.5999891917},
{"learn":[0.3378062391],"iteration":340,"passed_time":0.3089087024,"remaining_time":0.5987377497},
{"learn":[0.3374200161],"iteration":341,"passed_time":0.3096587684,"remaining_time":0.5975233712},
{"learn":[0.3373136528],"iteration":342,"passed_time":0.3104222944,"remaining_time":0.5963375656},
{"learn":[0.337080858],"iteration":343,"passed_time":0.3111459901,"remaining_time":0.5950780453},
{"learn":[0.3368807227],"iteration":344,"passed_time":0.311885036,"remaining_time":0.5938508679},
{"learn":[0.3366300522],"iteration":345,"passed_time":0.3125821115,"remaining_time":0.5925469592},
{"learn":[0.3361718636],"iteration":346,"passed_time":0.3132635169,"remaining_time":0.5912169842},
{"learn":[0.3358435449],"iteration":347,"passed_time":0.3139637024,"remaining_time":0.5899260345},
{"learn":[0.3356906222],"iteration":348,"passed_time":0.314667048,"remaining_time":0.5886443915},
{"learn":[0.3353990664],"iteration":349,"passed_time":0.3153710335,"remaining_time":0.5873672545},
{"learn":[0.3352462784],"iteration":350,"passed_time":0.3160714091,"remaining_time":0.5860866986},
{"learn":[0.3350237528],"iteration":351,"passed_time":0.3167420544,"remaining_time":0.5847545619},
{"learn":[0.3347089988],"iteration":352,"passed_time":0.3174357399,"remaining_time":0.5834685332},
{"learn":[0.3343800224],"iteration":353,"passed_time":0.3181188753,"remaining_time":0.5821665536},
{"learn":[0.3340352011],"iteration":354,"passed_time":0.3187967006,"remaining_time":0.5808583952},
{"learn":[0.3338064266],"iteration":355,"passed_time":0.3194843861,"remaining_time":0.579571675},
{"learn":[0.3335413502],"iteration":356,"passed_time":0.3202006317,"remaining_time":0.5783399051},
{"learn":[0.3333427549],"iteration":357,"passed_time":0.3208752971,"remaining_time":0.5770362485},
{"learn":[0.3331459143],"iteration":358,"passed_time":0.3215718026,"remaining_time":0.5757752108},
{"learn":[0.3327694362],"iteration":359,"passed_time":0.3222446579,"remaining_time":0.5744751561},
{"learn":[0.332433241],"iteration":360,"passed_time":0.3229460234,"remaining_time":0.5732291916},
{"learn":[0.3321659761],"iteration":361,"passed_time":0.3236278888,"remaining_time":0.5719517814},
{"learn":[0.3319902369],"iteration":362,"passed_time":0.3243099942,"remaining_time":0.5706780838},
{"learn":[0.3318082489],"iteration":363,"passed_time":0.3249721495,"remaining_time":0.5693726916},
{"learn":[0.3315882851],"iteration":364,"passed_time":0.3256657349,"remaining_time":0.568125664},
{"learn":[0.3312026766],"iteration":365,"passed_time":0.3263930107,"remaining_time":0.5669401884},
{"learn":[0.3309742761],"iteration":366,"passed_time":0.3271447066,"remaining_time":0.5657994516},
{"learn":[0.3308502015],"iteration":367,"passed_time":0.3278951226,"remaining_time":0.5646586307},
{"learn":[0.3305498564],"iteration":368,"passed_time":0.3286462585,"remaining_time":0.5635211661},
{"learn":[0.3303462817],"iteration":369,"passed_time":0.3293964544,"remaining_time":0.5623841905},
{"learn":[0.33017818],"iteration":370,"passed_time":0.3301406803,"remaining_time":0.5612391566},
{"learn":[0.3298883283],"iteration":371,"passed_time":0.330861256,"remaining_time":0.5600562501},
{"learn":[0.3296482504],"iteration":372,"passed_time":0.3316324721,"remaining_time":0.5589611828},
{"learn":[0.3294156651],"iteration":373,"passed_time":0.3323600179,"remaining_time":0.5577945608},
{"learn":[0.3292762359],"iteration":374,"passed_time":0.3331035938,"remaining_time":0.5566570751},
{"learn":[0.329105142],"iteration":375,"passed_time":0.3338531397,"remaining_time":0.5555316244},
{"learn":[0.3289328636],"iteration":376,"passed_time":0.3345887555,"remaining_time":0.5543850922},
{"learn":[0.3287432591],"iteration":377,"passed_time":0.3353358514,"remaining_time":0.5532596806},
{"learn":[0.3283998784],"iteration":378,"passed_time":0.3360624371,"remaining_time":0.5521025753},
{"learn":[0.3282923764],"iteration":379,"passed_time":0.3368523834,"remaining_time":0.5510513924},
{"learn":[0.3280515178],"iteration":380,"passed_time":0.3376060494,"remaining_time":0.5499424857},
{"learn":[0.3277902162],"iteration":381,"passed_time":0.3383811055,"remaining_time":0.5488701396},
{"learn":[0.3276385883],"iteration":382,"passed_time":0.3391321314,"remaining_time":0.5477605369},
{"learn":[0.3275117892],"iteration":383,"passed_time":0.3398851374,"remaining_time":0.5466559912},
{"learn":[0.3272247278],"iteration":384,"passed_time":0.3406102631,"remaining_time":0.5455086245},
{"learn":[0.3270989795],"iteration":385,"passed_time":0.3413354588,"remaining_time":0.5443635629},
{"learn":[0.3269715374],"iteration":386,"passed_time":0.3420989149,"remaining_time":0.5432814374},
{"learn":[0.3267679192],"iteration":387,"passed_time":0.3428374907,"remaining_time":0.5421616132},
{"learn":[0.3265941078],"iteration":388,"passed_time":0.3435560564,"remaining_time":0.5410122434},
{"learn":[0.326362471],"iteration":389,"passed_time":0.3443118924,"remaining_time":0.539923533},
{"learn":[0.3260746261],"iteration":390,"passed_time":0.3450677483,"remaining_time":0.5388365609},
{"learn":[0.3259218415],"iteration":391,"passed_time":0.3458218143,"remaining_time":0.537748499},
{"learn":[0.3256525126],"iteration":392,"passed_time":0.34654077,"remaining_time":0.5366077739},
{"learn":[0.32549815],"iteration":393,"passed_time":0.3472796358,"remaining_time":0.5354998965},
{"learn":[0.32531209],"iteration":394,"passed_time":0.3480171317,"remaining_time":0.5343917885},
{"learn":[0.3250710314],"iteration":395,"passed_time":0.3487338573,"remaining_time":0.533253797},
{"learn":[0.3249228995],"iteration":396,"passed_time":0.3494837033,"remaining_time":0.5321683663},
{"learn":[0.3246997812],"iteration":397,"passed_time":0.3502538394,"remaining_time":0.5311153937},
{"learn":[0.3244835978],"iteration":398,"passed_time":0.3509794651,"remaining_time":0.5299966294},
{"learn":[0.3243165889],"iteration":399,"passed_time":0.3517108809,"remaining_time":0.5288885427},
{"learn":[0.3240545425],"iteration":400,"passed_time":0.3525403374,"remaining_time":0.5279291553},
{"learn":[0.3237653107],"iteration":401,"passed_time":0.3532647532,"remaining_time":0.5268137715},
{"learn":[0.3236058554],"iteration":402,"passed_time":0.3540126791,"remaining_time":0.5257352473},
{"learn":[0.3234473233],"iteration":403,"passed_time":0.3547694851,"remaining_time":0.5246714965},
{"learn":[0.3232296004],"iteration":404,"passed_time":0.3555021308,"remaining_time":0.5235736828},
{"learn":[0.3230191435],"iteration":405,"passed_time":0.3562442767,"remaining_time":0.5224916059},
{"learn":[0.3227753852],"iteration":406,"passed_time":0.3569918726,"remaining_time":0.5214191637},
{"learn":[0.3225040669],"iteration":407,"passed_time":0.3577092183,"remaining_time":0.5203043175},
{"learn":[0.3224251381],"iteration":408,"passed_time":0.3584554342,"remaining_time":0.5192332392},
{"learn":[0.3222506406],"iteration":409,"passed_time":0.3591792499,"remaining_time":0.5181314363},
{"learn":[0.3221004809],"iteration":410,"passed_time":0.3599017056,"remaining_time":0.5170295235},
{"learn":[0.321822688],"iteration":411,"passed_time":0.3606180613,"remaining_time":0.51592073},
{"learn":[0.3216335109],"iteration":412,"passed_time":0.3613588472,"remaining_time":0.5148486487},
{"learn":[0.3214458528],"iteration":413,"passed_time":0.3621096231,"remaining_time":0.5137923466},
{"learn":[0.3212302663],"iteration":414,"passed_time":0.3628336388,"remaining_time":0.512699707},
{"learn":[0.3210830276],"iteration":415,"passed_time":0.3635511145,"remaining_time":0.5115996406},
{"learn":[0.3207921917],"iteration":416,"passed_time":0.3642971604,"remaining_time":0.5105414531},
{"learn":[0.320623879],"iteration":417,"passed_time":0.3650861166,"remaining_time":0.509544652},
{"learn":[0.3204702592],"iteration":418,"passed_time":0.3657820921,"remaining_time":0.5084196065},
{"learn":[0.3203196592],"iteration":419,"passed_time":0.3665444682,"remaining_time":0.5073885239},
{"learn":[0.3200024119],"iteration":420,"passed_time":0.3672701339,"remaining_time":0.5063081132},
{"learn":[0.3198690094],"iteration":421,"passed_time":0.3680135798,"remaining_time":0.5052537984},
{"learn":[0.3196597805],"iteration":422,"passed_time":0.3687392255,"remaining_time":0.5041766188},
{"learn":[0.3193545219],"iteration":423,"passed_time":0.3694974415,"remaining_time":0.5031454523},
{"learn":[0.319105725],"iteration":424,"passed_time":0.3702245673,"remaining_time":0.5020734108},
{"learn":[0.3188137344],"iteration":425,"passed_time":0.370945513,"remaining_time":0.5009946457},
{"learn":[0.3186169896],"iteration":426,"passed_time":0.371713589,"remaining_time":0.4999809543},
{"learn":[0.3182877065],"iteration":427,"passed_time":0.3724348447,"remaining_time":0.4989056936},
{"learn":[0.3179816534],"iteration":428,"passed_time":0.3732095209,"remaining_time":0.4979033561},
{"learn":[0.3176921742],"iteration":429,"passed_time":0.3739175265,"remaining_time":0.4968134967},
{"learn":[0.3175368461],"iteration":430,"passed_time":0.374622992,"remaining_time":0.4957220522},
{"learn":[0.3173507679],"iteration":431,"passed_time":0.3753946081,"remaining_time":0.4947195764},
{"learn":[0.3171103626],"iteration":432,"passed_time":0.376138934,"remaining_time":0.4936823509},
{"learn":[0.3167721886],"iteration":433,"passed_time":0.3768546597,"remaining_time":0.4926090932},
{"learn":[0.316617039],"iteration":434,"passed_time":0.3775664053,"remaining_time":0.4915323018},
{"learn":[0.3162019813],"iteration":435,"passed_time":0.3782985011,"remaining_time":0.4904835738},
{"learn":[0.315993004],"iteration":436,"passed_time":0.3789956566,"remaining_time":0.4893911804},
{"learn":[0.3156844886],"iteration":437,"passed_time":0.3797515326,"remaining_time":0.4883761128},
{"learn":[0.3154229759],"iteration":438,"passed_time":0.3804928984,"remaining_time":0.4873436439},
{"learn":[0.3151628764],"iteration":439,"passed_time":0.3811802039,"remaining_time":0.4862435403},
{"learn":[0.3148993553],"iteration":440,"passed_time":0.3818890895,"remaining_time":0.4851727296},
{"learn":[0.3146587437],"iteration":441,"passed_time":0.3827254061,"remaining_time":0.4842647995},
{"learn":[0.3143907185],"iteration":442,"passed_time":0.3836918637,"remaining_time":0.4835211948},
{"learn":[0.3142449323],"iteration":443,"passed_time":0.3844349996,"remaining_time":0.4824962975},
{"learn":[0.3140453224],"iteration":444,"passed_time":0.3851538753,"remaining_time":0.4814423441},
{"learn":[0.3139092117],"iteration":445,"passed_time":0.3858573509,"remaining_time":0.4803707244},
{"learn":[0.313791336],"iteration":446,"passed_time":0.3865315362,"remaining_time":0.4792644384},
{"learn":[0.3134587405],"iteration":447,"passed_time":0.3872430018,"remaining_time":0.478206123},
{"learn":[0.3132288282],"iteration":448,"passed_time":0.3879244372,"remaining_time":0.4771124216},
{"learn":[0.3128080894],"iteration":449,"passed_time":0.3886064626,"remaining_time":0.4760212793},
{"learn":[0.3126117344],"iteration":450,"passed_time":0.3893013081,"remaining_time":0.4749475959},
{"learn":[0.3124470129],"iteration":451,"passed_time":0.3899996436,"remaining_time":0.473879833},
{"learn":[0.3122099056],"iteration":452,"passed_time":0.390677049,"remaining_time":0.4727883756},
{"learn":[0.3120416395],"iteration":453,"passed_time":0.3913619844,"remaining_time":0.4717078222},
{"learn":[0.3117205407],"iteration":454,"passed_time":0.3921480506,"remaining_time":0.4707504132},
{"learn":[0.3115733168],"iteration":455,"passed_time":0.3928431961,"remaining_time":0.469685052},
{"learn":[0.3114808503],"iteration":456,"passed_time":0.3935196014,"remaining_time":0.4685989991},
{"learn":[0.3113195985],"iteration":457,"passed_time":0.394351238,"remaining_time":0.4676988425},
{"learn":[0.3110714067],"iteration":458,"passed_time":0.3962923634,"remaining_time":0.4681095384},
{"learn":[0.3107819983],"iteration":459,"passed_time":0.39713339,"remaining_time":0.467215753},
{"learn":[0.3106680587],"iteration":460,"passed_time":0.397887826,"remaining_time":0.4662207352},
{"learn":[0.3105887034],"iteration":461,"passed_time":0.3985816715,"remaining_time":0.4651560504},
{"learn":[0.3103679038],"iteration":462,"passed_time":0.399406258,"remaining_time":0.4642449362},
{"learn":[0.3102442018],"iteration":463,"passed_time":0.4001058235,"remaining_time":0.4631894631},
{"learn":[0.3100153475],"iteration":464,"passed_time":0.400804509,"remaining_time":0.4621345093},
{"learn":[0.3097173564],"iteration":465,"passed_time":0.4015691451,"remaining_time":0.4611568247},
{"learn":[0.3096385074],"iteration":466,"passed_time":0.4022381904,"remaining_time":0.4600707199},
{"learn":[0.3095077834],"iteration":467,"passed_time":0.4029248258,"remaining_time":0.4590064397},
{"learn":[0.3092899342],"iteration":468,"passed_time":0.4036910519,"remaining_time":0.4580340781},
{"learn":[0.3091140318],"iteration":469,"passed_time":0.4043556471,"remaining_time":0.4569477462},
{"learn":[0.3089786334],"iteration":470,"passed_time":0.4050477226,"remaining_time":0.4558941388},
{"learn":[0.3087472652],"iteration":471,"passed_time":0.4057427281,"remaining_time":0.4548453512},
{"learn":[0.3085941253],"iteration":472,"passed_time":0.4064365136,"remaining_time":0.4537967005},
{"learn":[0.3084907072],"iteration":473,"passed_time":0.4071082389,"remaining_time":0.4527250183},
{"learn":[0.3083128281],"iteration":474,"passed_time":0.4077690341,"remaining_time":0.4516429175},
{"learn":[0.3080593372],"iteration":475,"passed_time":0.4084389394,"remaining_time":0.4505726405},
{"learn":[0.3078399117],"iteration":476,"passed_time":0.4091673252,"remaining_time":0.4495683005},
{"learn":[0.3076349659],"iteration":477,"passed_time":0.4098478505,"remaining_time":0.4485127421},
{"learn":[0.3074442592],"iteration":478,"passed_time":0.4107525477,"remaining_time":0.4477030907},
{"learn":[0.307020453],"iteration":479,"passed_time":0.4114592533,"remaining_time":0.4466781038},
{"learn":[0.306793012],"iteration":480,"passed_time":0.4121604588,"remaining_time":0.4456484961},
{"learn":[0.3066413541],"iteration":481,"passed_time":0.4128560643,"remaining_time":0.4446142231},
{"learn":[0.3064860855],"iteration":482,"passed_time":0.4135641799,"remaining_time":0.4435947739},
{"learn":[0.3063533598],"iteration":483,"passed_time":0.4142575454,"remaining_time":0.442560856},
{"learn":[0.3061486482],"iteration":484,"passed_time":0.4150972821,"remaining_time":0.4416840914},
{"learn":[0.3060127441],"iteration":485,"passed_time":0.4157739874,"remaining_time":0.4406347},
{"learn":[0.3058639815],"iteration":486,"passed_time":0.416481513,"remaining_time":0.4396193748},
{"learn":[0.3057022844],"iteration":487,"passed_time":0.4171703584,"remaining_time":0.4385856746},
{"learn":[0.3054856823],"iteration":488,"passed_time":0.4178395137,"remaining_time":0.4375327695},
{"learn":[0.3053440914],"iteration":489,"passed_time":0.4185230191,"remaining_time":0.4364964003},
{"learn":[0.3051506802],"iteration":490,"passed_time":0.4192113846,"remaining_time":0.4354665199},
{"learn":[0.3049870849],"iteration":491,"passed_time":0.4199198102,"remaining_time":0.4344587853},
{"learn":[0.3047534829],"iteration":492,"passed_time":0.4206238157,"remaining_time":0.4334477126},
{"learn":[0.3046623678],"iteration":493,"passed_time":0.4213265913,"remaining_time":0.4324366231},
{"learn":[0.3044593084],"iteration":494,"passed_time":0.4219839365,"remaining_time":0.4313803399},
{"learn":[0.3042160691],"iteration":495,"passed_time":0.422678912,"remaining_time":0.4303639831},
{"learn":[0.304047483],"iteration":496,"passed_time":0.4233829276,"remaining_time":0.4293580898},
{"learn":[0.3039315333],"iteration":497,"passed_time":0.4241527536,"remaining_time":0.428419884},
{"learn":[0.3036538211],"iteration":498,"passed_time":0.4248400191,"remaining_time":0.4273992963},
{"learn":[0.3035221946],"iteration":499,"passed_time":0.4255241145,"remaining_time":0.4263768682},
{"learn":[0.3033733677],"iteration":500,"passed_time":0.4262089399,"remaining_time":0.425356522},
{"learn":[0.3030829305],"iteration":501,"passed_time":0.4268864253,"remaining_time":0.4243302191},
{"learn":[0.3028301852],"iteration":502,"passed_time":0.4275940009,"remaining_time":0.4233350965},
{"learn":[0.3027016667],"iteration":503,"passed_time":0.4282653562,"remaining_time":0.4223054009},
{"learn":[0.3024626473],"iteration":504,"passed_time":0.4289535916,"remaining_time":0.421293706},
{"learn":[0.302142928],"iteration":505,"passed_time":0.4296509071,"remaining_time":0.4202921745},
{"learn":[0.3020110645],"iteration":506,"passed_time":0.4304372733,"remaining_time":0.4193786082},
{"learn":[0.3018147202],"iteration":507,"passed_time":0.4311363989,"remaining_time":0.4183808841},
{"learn":[0.3015257158],"iteration":508,"passed_time":0.4318426345,"remaining_time":0.4173912077},
{"learn":[0.3014616287],"iteration":509,"passed_time":0.43253973,"remaining_time":0.4163938461},
{"learn":[0.3012794372],"iteration":510,"passed_time":0.4332658057,"remaining_time":0.415425449},
{"learn":[0.3011337908],"iteration":511,"passed_time":0.433934451,"remaining_time":0.4144031548},
{"learn":[0.3009527967],"iteration":512,"passed_time":0.4346244264,"remaining_time":0.4134025306},
{"learn":[0.3008437819],"iteration":513,"passed_time":0.4353155819,"remaining_time":0.4124042355},
{"learn":[0.3005990989],"iteration":514,"passed_time":0.4360405576,"remaining_time":0.4114390476},
{"learn":[0.3003898823],"iteration":515,"passed_time":0.4367299231,"remaining_time":0.4104413258},
{"learn":[0.3002860677],"iteration":516,"passed_time":0.4374025884,"remaining_time":0.4094291671},
{"learn":[0.3002027167],"iteration":517,"passed_time":0.4380964839,"remaining_time":0.4084381146},
{"learn":[0.3000012555],"iteration":518,"passed_time":0.4388005695,"remaining_time":0.4074576716},
{"learn":[0.2998489986],"iteration":519,"passed_time":0.439494645,"remaining_time":0.4064690358},
{"learn":[0.2997538303],"iteration":520,"passed_time":0.4401972705,"remaining_time":0.4054894088},
{"learn":[0.2996232958],"iteration":521,"passed_time":0.4408768459,"remaining_time":0.4044896974},
{"learn":[0.2994448575],"iteration":522,"passed_time":0.4416427019,"remaining_time":0.4035700552},
{"learn":[0.2993314322],"iteration":523,"passed_time":0.4436122775,"remaining_time":0.403746547},
{"learn":[0.2991783225],"iteration":524,"passed_time":0.4446155754,"remaining_time":0.4030389281},
{"learn":[0.2990726252],"iteration":525,"passed_time":0.4453786715,"remaining_time":0.4021133148},
{"learn":[0.2989190949],"iteration":526,"passed_time":0.4462218781,"remaining_time":0.4012603581},
{"learn":[0.2988005567],"iteration":527,"passed_time":0.4468933035,"remaining_time":0.4002535849},
{"learn":[0.2986313875],"iteration":528,"passed_time":0.4475690088,"remaining_time":0.3992518999},
{"learn":[0.2985381505],"iteration":529,"passed_time":0.4482522142,"remaining_time":0.3982581109},
{"learn":[0.298224566],"iteration":530,"passed_time":0.4489353796,"remaining_time":0.3972654585},
{"learn":[0.2980634034],"iteration":531,"passed_time":0.449616095,"remaining_time":0.3962718125},
{"learn":[0.2979403726],"iteration":532,"passed_time":0.4503267906,"remaining_time":0.3953056602},
{"learn":[0.2977336188],"iteration":533,"passed_time":0.4510210661,"remaining_time":0.3943261103},
{"learn":[0.29760538],"iteration":534,"passed_time":0.4519756936,"remaining_time":0.39357434},
{"learn":[0.2973738363],"iteration":535,"passed_time":0.4526892693,"remaining_time":0.3926127494},
{"learn":[0.2972379552],"iteration":536,"passed_time":0.453417575,"remaining_time":0.3916648083},
{"learn":[0.297055445],"iteration":537,"passed_time":0.4541199206,"remaining_time":0.3906953507},
{"learn":[0.2969528095],"iteration":538,"passed_time":0.4547934659,"remaining_time":0.3897022078},
{"learn":[0.2967686989],"iteration":539,"passed_time":0.4554670012,"remaining_time":0.3887102422},
{"learn":[0.2965568878],"iteration":540,"passed_time":0.4561464066,"remaining_time":0.3877244456},
{"learn":[0.2963248458],"iteration":541,"passed_time":0.4568447621,"remaining_time":0.3867558245},
{"learn":[0.2961619092],"iteration":542,"passed_time":0.4576035781,"remaining_time":0.3858391793},
{"learn":[0.2960710033],"iteration":543,"passed_time":0.458345564,"remaining_time":0.3849089819},
{"learn":[0.2958414405],"iteration":544,"passed_time":0.45910042,"remaining_time":0.383990241},
{"learn":[0.2956297886],"iteration":545,"passed_time":0.4597943155,"remaining_time":0.3830213197},
{"learn":[0.2954730419],"iteration":546,"passed_time":0.4604672608,"remaining_time":0.3820360241},
{"learn":[0.2954176279],"iteration":547,"passed_time":0.4616240799,"remaining_time":0.3814517077},
{"learn":[0.2953194499],"iteration":548,"passed_time":0.4625062669,"remaining_time":0.3806392817},
{"learn":[0.2951700407],"iteration":549,"passed_time":0.4633072332,"remaining_time":0.3797600272},
{"learn":[0.2949806086],"iteration":550,"passed_time":0.464039039,"remaining_time":0.3788245973},
{"learn":[0.2947492712],"iteration":551,"passed_time":0.464790755,"remaining_time":0.3779060948},
{"learn":[0.2946293823],"iteration":552,"passed_time":0.4655352808,"remaining_time":0.3769823742},
{"learn":[0.2944546474],"iteration":553,"passed_time":0.4662656466,"remaining_time":0.3760478814},
{"learn":[0.2942443283],"iteration":554,"passed_time":0.4670540229,"remaining_time":0.3751607223},
{"learn":[0.2941022118],"iteration":555,"passed_time":0.4678981695,"remaining_time":0.3743185356},
{"learn":[0.2940060549],"iteration":556,"passed_time":0.4686830657,"remaining_time":0.3734291333},
{"learn":[0.2938082622],"iteration":557,"passed_time":0.4694310017,"remaining_time":0.3725107769},
{"learn":[0.2935500835],"iteration":558,"passed_time":0.4704204295,"remaining_time":0.3717838878},
{"learn":[0.293298609],"iteration":559,"passed_time":0.4725180461,"remaining_time":0.3719283368},
{"learn":[0.2931172777],"iteration":560,"passed_time":0.4734149532,"remaining_time":0.3711235079},
{"learn":[0.2929295857],"iteration":561,"passed_time":0.4741761492,"remaining_time":0.3702123945},
{"learn":[0.2927322406],"iteration":562,"passed_time":0.4749223951,"remaining_time":0.3692901898},
{"learn":[0.292532106],"iteration":563,"passed_time":0.4757427516,"remaining_time":0.368426003},
{"learn":[0.2923160718],"iteration":564,"passed_time":0.4764820174,"remaining_time":0.3674994283},
{"learn":[0.2921490101],"iteration":565,"passed_time":0.4773960546,"remaining_time":0.3667077659},
{"learn":[0.2920091714],"iteration":566,"passed_time":0.4781582107,"remaining_time":0.3657994792},
{"learn":[0.2918421538],"iteration":567,"passed_time":0.4789303668,"remaining_time":0.3648993271},
{"learn":[0.2916471549],"iteration":568,"passed_time":0.4796540825,"remaining_time":0.3639628689},
{"learn":[0.2914616118],"iteration":569,"passed_time":0.4805962799,"remaining_time":0.3631922678},
{"learn":[0.2913257838],"iteration":570,"passed_time":0.4813749461,"remaining_time":0.3622979857},
{"learn":[0.2911500782],"iteration":571,"passed_time":0.4821873625,"remaining_time":0.3614294066},
{"learn":[0.2909320298],"iteration":572,"passed_time":0.4829347684,"remaining_time":0.3605124932},
{"learn":[0.2906868208],"iteration":573,"passed_time":0.4837200246,"remaining_time":0.3596243115},
{"learn":[0.2905755821],"iteration":574,"passed_time":0.4844436804,"remaining_time":0.3586908783},
{"learn":[0.2904785164],"iteration":575,"passed_time":0.4851798462,"remaining_time":0.3577673996},
{"learn":[0.2902756124],"iteration":576,"passed_time":0.4858898518,"remaining_time":0.3568253599},
{"learn":[0.2899797631],"iteration":577,"passed_time":0.4866362477,"remaining_time":0.3559107392},
{"learn":[0.2899124398],"iteration":578,"passed_time":0.4873458533,"remaining_time":0.3549699035},
{"learn":[0.2897395486],"iteration":579,"passed_time":0.488322041,"remaining_time":0.3542232422},
{"learn":[0.2896551028],"iteration":580,"passed_time":0.489074517,"remaining_time":0.3533141769},
{"learn":[0.2895274369],"iteration":581,"passed_time":0.489831903,"remaining_time":0.3524091832},
{"learn":[0.2893876613],"iteration":582,"passed_time":0.4905697588,"remaining_time":0.3514907035},
{"learn":[0.289235267],"iteration":583,"passed_time":0.4912924745,"remaining_time":0.3505620401},
{"learn":[0.2890395309],"iteration":584,"passed_time":0.4919960801,"remaining_time":0.3496205021},
{"learn":[0.2887971446],"iteration":585,"passed_time":0.4928579469,"remaining_time":0.3487917778},
{"learn":[0.2886673421],"iteration":586,"passed_time":0.4935958227,"remaining_time":0.3478755542},
{"learn":[0.2884696276],"iteration":587,"passed_time":0.4943236185,"remaining_time":0.3469528634},
{"learn":[0.2883485369],"iteration":588,"passed_time":0.4952879961,"remaining_time":0.3461962014},
{"learn":[0.2882308599],"iteration":589,"passed_time":0.4960652122,"remaining_time":0.3453085518},
{"learn":[0.2880516116],"iteration":590,"passed_time":0.4968166582,"remaining_time":0.3444034122},
{"learn":[0.287924582],"iteration":591,"passed_time":0.4975726142,"remaining_time":0.3435019062},
{"learn":[0.2877552769],"iteration":592,"passed_time":0.4984611212,"remaining_time":0.3426920208},
{"learn":[0.287559447],"iteration":593,"passed_time":0.4993408181,"remaining_time":0.3418758384},
{"learn":[0.2874437497],"iteration":594,"passed_time":0.5012071329,"remaining_time":0.3417321361},
{"learn":[0.2871812617],"iteration":595,"passed_time":0.5023484419,"remaining_time":0.3410903706},
{"learn":[0.2869856768],"iteration":596,"passed_time":0.5032950894,"remaining_time":0.3403153037},
{"learn":[0.2868639047],"iteration":597,"passed_time":0.504001765,"remaining_time":0.3393780729},
{"learn":[0.2866642241],"iteration":598,"passed_time":0.5050261031,"remaining_time":0.3386546277},
{"learn":[0.286549306],"iteration":599,"passed_time":0.5058310495,"remaining_time":0.3377836724},
{"learn":[0.2864275842],"iteration":600,"passed_time":0.5066888262,"remaining_time":0.3369480694},
{"learn":[0.2863050989],"iteration":601,"passed_time":0.5076115735,"remaining_time":0.3361554181},
{"learn":[0.2861923582],"iteration":602,"passed_time":0.5091251755,"remaining_time":0.3357519845},
{"learn":[0.2861171321],"iteration":603,"passed_time":0.5103944855,"remaining_time":0.3351844383},
{"learn":[0.2858771133],"iteration":604,"passed_time":0.5113464331,"remaining_time":0.3344070216},
{"learn":[0.2858112443],"iteration":605,"passed_time":0.5122749704,"remaining_time":0.3336137824},
{"learn":[0.2857240516],"iteration":606,"passed_time":0.5138142026,"remaining_time":0.3332161413},
{"learn":[0.2854857501],"iteration":607,"passed_time":0.5146598493,"remaining_time":0.3323668219},
{"learn":[0.2851748725],"iteration":608,"passed_time":0.5159369394,"remaining_time":0.3317949725},
{"learn":[0.2849792645],"iteration":609,"passed_time":0.5168406765,"remaining_time":0.330981714},
{"learn":[0.2848862217],"iteration":610,"passed_time":0.5184923796,"remaining_time":0.3306451404},
{"learn":[0.284679634],"iteration":611,"passed_time":0.5196765789,"remaining_time":0.3300073856},
{"learn":[0.2845303216],"iteration":612,"passed_time":0.5207835577,"remaining_time":0.3293190144},
{"learn":[0.2844079073],"iteration":613,"passed_time":0.5223541201,"remaining_time":0.3289211914},
{"learn":[0.2842151317],"iteration":614,"passed_time":0.5235206193,"remaining_time":0.3282661864},
{"learn":[0.2840702001],"iteration":615,"passed_time":0.5243970463,"remaining_time":0.3274283996},
{"learn":[0.2840037738],"iteration":616,"passed_time":0.5256464361,"remaining_time":0.3268223783},
{"learn":[0.2838437772],"iteration":617,"passed_time":0.5266656742,"remaining_time":0.3260717788},
{"learn":[0.28369678],"iteration":618,"passed_time":0.5275380011,"remaining_time":0.3252297385},
{"learn":[0.2835802261],"iteration":619,"passed_time":0.5283730577,"remaining_time":0.3243647204},
{"learn":[0.2834160661],"iteration":620,"passed_time":0.5295267268,"remaining_time":0.3236945636},
{"learn":[0.2833315273],"iteration":621,"passed_time":0.5304081838,"remaining_time":0.3228571553},
{"learn":[0.283225035],"iteration":622,"passed_time":0.5314822123,"remaining_time":0.3221363248},
{"learn":[0.283137414],"iteration":623,"passed_time":0.5323581292,"remaining_time":0.3212947939},
{"learn":[0.2829061217],"iteration":624,"passed_time":0.5333609271,"remaining_time":0.3205294033},
{"learn":[0.2826910548],"iteration":625,"passed_time":0.534107683,"remaining_time":0.3196100375},
{"learn":[0.2825741711],"iteration":626,"passed_time":0.5349377396,"remaining_time":0.3187408576},
{"learn":[0.2824789638],"iteration":627,"passed_time":0.535869347,"remaining_time":0.3179320527},
{"learn":[0.2822633151],"iteration":628,"passed_time":0.5368562248,"remaining_time":0.3171555086},
{"learn":[0.2820939505],"iteration":629,"passed_time":0.5376967414,"remaining_time":0.3162922008},
{"learn":[0.2819029015],"iteration":630,"passed_time":0.5386163387,"remaining_time":0.3154752841},
{"learn":[0.2816411398],"iteration":631,"passed_time":0.5398520084,"remaining_time":0.3148423758},
{"learn":[0.2814683202],"iteration":632,"passed_time":0.5412151792,"remaining_time":0.3142815993},
{"learn":[0.2812750398],"iteration":633,"passed_time":0.5420993362,"remaining_time":0.3134413224},
{"learn":[0.2811498969],"iteration":634,"passed_time":0.5429274128,"remaining_time":0.3125686209},
{"learn":[0.280977295],"iteration":635,"passed_time":0.5439352207,"remaining_time":0.3117990872},
{"learn":[0.2808131488],"iteration":636,"passed_time":0.5449697289,"remaining_time":0.3110440434},
{"learn":[0.2805769145],"iteration":637,"passed_time":0.5459277765,"remaining_time":0.3102446705},
{"learn":[0.2805154166],"iteration":638,"passed_time":0.5468422437,"remaining_time":0.309420141},
{"learn":[0.2804097288],"iteration":639,"passed_time":0.5479881128,"remaining_time":0.3087256973},
{"learn":[0.2801519593],"iteration":640,"passed_time":0.5488570896,"remaining_time":0.3078745237},
{"learn":[0.2800061215],"iteration":641,"passed_time":0.5498628876,"remaining_time":0.3070997095},
{"learn":[0.2798205541],"iteration":642,"passed_time":0.5513577194,"remaining_time":0.306596115},
{"learn":[0.2796635638],"iteration":643,"passed_time":0.5527084201,"remaining_time":0.3060096385},
{"learn":[0.2794486659],"iteration":644,"passed_time":0.5536875278,"remaining_time":0.3052159509},
{"learn":[0.2793270299],"iteration":645,"passed_time":0.5549257376,"remaining_time":0.3045638932},
{"learn":[0.2791161729],"iteration":646,"passed_time":0.5558367448,"remaining_time":0.3037312243},
{"learn":[0.2790169042],"iteration":647,"passed_time":0.5572264858,"remaining_time":0.3031587682},
{"learn":[0.2788986725],"iteration":648,"passed_time":0.5587005975,"remaining_time":0.3026294903},
{"learn":[0.2786302625],"iteration":649,"passed_time":0.5598619767,"remaining_time":0.3019286469},
{"learn":[0.2784776792],"iteration":650,"passed_time":0.5614707494,"remaining_time":0.3014666024},
{"learn":[0.2783851414],"iteration":651,"passed_time":0.5627627096,"remaining_time":0.3008316789},
{"learn":[0.2783229837],"iteration":652,"passed_time":0.5637288872,"remaining_time":0.3000213556},
{"learn":[0.2782201508],"iteration":653,"passed_time":0.5647963857,"remaining_time":0.2992642411},
{"learn":[0.2780304352],"iteration":654,"passed_time":0.5815810684,"remaining_time":0.3067973526},
{"learn":[0.2779132058],"iteration":655,"passed_time":0.6216889355,"remaining_time":0.3265053341},
{"learn":[0.2777138542],"iteration":656,"passed_time":0.6246005585,"remaining_time":0.3265823042},
{"learn":[0.2775858324],"iteration":657,"passed_time":0.6264658633,"remaining_time":0.3261055179},
{"learn":[0.2774694377],"iteration":658,"passed_time":0.6278951746,"remaining_time":0.3253985631},
{"learn":[0.277328224],"iteration":659,"passed_time":0.6293242159,"remaining_time":0.3246892768},
{"learn":[0.2771671384],"iteration":660,"passed_time":0.6301462224,"remaining_time":0.3236660142},
{"learn":[0.2768743054],"iteration":661,"passed_time":0.6308836782,"remaining_time":0.3226001259},
{"learn":[0.2766953587],"iteration":662,"passed_time":0.6316047239,"remaining_time":0.3215268761},
{"learn":[0.2766184887],"iteration":663,"passed_time":0.6323271496,"remaining_time":0.320455388},
{"learn":[0.2764525517],"iteration":664,"passed_time":0.6330843056,"remaining_time":0.3194024735},
{"learn":[0.2762735344],"iteration":665,"passed_time":0.6341084137,"remaining_time":0.3184845266},
{"learn":[0.2761031517],"iteration":666,"passed_time":0.6470386859,"remaining_time":0.323519343},
{"learn":[0.275928012],"iteration":667,"passed_time":0.6505287135,"remaining_time":0.3238013986},
{"learn":[0.2758025518],"iteration":668,"passed_time":0.6561307778,"remaining_time":0.3251186938},
{"learn":[0.2756006776],"iteration":669,"passed_time":0.6573499375,"remaining_time":0.3242533324},
{"learn":[0.2754054616],"iteration":670,"passed_time":0.6590865912,"remaining_time":0.3236410276},
{"learn":[0.2752510719],"iteration":671,"passed_time":0.6602067201,"remaining_time":0.3227240003},
{"learn":[0.2750637576],"iteration":672,"passed_time":0.6612908786,"remaining_time":0.321788865},
{"learn":[0.2749280166],"iteration":673,"passed_time":0.6623729072,"remaining_time":0.3208522552},
{"learn":[0.2747921427],"iteration":674,"passed_time":0.6634075154,"remaining_time":0.3198923479},
{"learn":[0.2746689703],"iteration":675,"passed_time":0.6645088541,"remaining_time":0.31896425},
{"learn":[0.2745508665],"iteration":676,"passed_time":0.6656607832,"remaining_time":0.3180598121},
{"learn":[0.2743969651],"iteration":677,"passed_time":0.666782032,"remaining_time":0.3171400507},
{"learn":[0.2742607832],"iteration":678,"passed_time":0.6677988101,"remaining_time":0.3161702331},
{"learn":[0.2740896749],"iteration":679,"passed_time":0.6688982688,"remaining_time":0.315239243},
{"learn":[0.2739699216],"iteration":680,"passed_time":0.6697822758,"remaining_time":0.3142066853},
{"learn":[0.2738062369],"iteration":681,"passed_time":0.6716277404,"remaining_time":0.3136235263},
{"learn":[0.2737403639],"iteration":682,"passed_time":0.6747252049,"remaining_time":0.3136186069},
{"learn":[0.2735684377],"iteration":683,"passed_time":0.6756584122,"remaining_time":0.3126033064},
{"learn":[0.273293592],"iteration":684,"passed_time":0.6767990712,"remaining_time":0.3116837828},
{"learn":[0.2731283811],"iteration":685,"passed_time":0.6777212085,"remaining_time":0.3106634445},
{"learn":[0.2730399531],"iteration":686,"passed_time":0.6785613252,"remaining_time":0.3096059691},
{"learn":[0.2728848423],"iteration":687,"passed_time":0.6803633894,"remaining_time":0.3089859935},
{"learn":[0.2728000228],"iteration":688,"passed_time":0.6814792883,"remaining_time":0.3080524108},
{"learn":[0.2726711941],"iteration":689,"passed_time":0.682462836,"remaining_time":0.3070587506},
{"learn":[0.2725595585],"iteration":690,"passed_time":0.6836517454,"remaining_time":0.306157086},
{"learn":[0.272481708],"iteration":691,"passed_time":0.6848496049,"remaining_time":0.3052585793},
{"learn":[0.2723545449],"iteration":692,"passed_time":0.6867423699,"remaining_time":0.3046674965},
{"learn":[0.272231739],"iteration":693,"passed_time":0.6879560595,"remaining_time":0.3037728055},
{"learn":[0.2721401447],"iteration":694,"passed_time":0.6892815699,"remaining_time":0.3029263384},
{"learn":[0.2719997295],"iteration":695,"passed_time":0.6902332075,"remaining_time":0.3019149569},
{"learn":[0.2719459738],"iteration":696,"passed_time":0.6910097136,"remaining_time":0.3008275046},
{"learn":[0.2718628154],"iteration":697,"passed_time":0.6918299801,"remaining_time":0.2997599053},
{"learn":[0.2717119404],"iteration":698,"passed_time":0.6987209346,"remaining_time":0.3013108901},
{"learn":[0.2715622868],"iteration":699,"passed_time":0.7006530399,"remaining_time":0.3007094592},
{"learn":[0.2714603405],"iteration":700,"passed_time":0.7014568462,"remaining_time":0.2996222815},
{"learn":[0.2713736002],"iteration":701,"passed_time":0.7022704526,"remaining_time":0.2985400783},
{"learn":[0.2710902131],"iteration":702,"passed_time":0.7030559089,"remaining_time":0.2974467307},
{"learn":[0.2708949533],"iteration":703,"passed_time":0.7038752053,"remaining_time":0.2963685075},
{"learn":[0.2707073829],"iteration":704,"passed_time":0.7047855425,"remaining_time":0.2953291691},
{"learn":[0.2706302059],"iteration":705,"passed_time":0.7056993798,"remaining_time":0.2942916562},
{"learn":[0.2705393309],"iteration":706,"passed_time":0.7065593966,"remaining_time":0.2932321575},
{"learn":[0.2703900829],"iteration":707,"passed_time":0.7074433135,"remaining_time":0.2921830941},
{"learn":[0.2702897395],"iteration":708,"passed_time":0.7083463107,"remaining_time":0.2911423396},
{"learn":[0.270204449],"iteration":709,"passed_time":0.7092135175,"remaining_time":0.2900873344},
{"learn":[0.2701734222],"iteration":710,"passed_time":0.7101120446,"remaining_time":0.2890456069},
{"learn":[0.2700651451],"iteration":711,"passed_time":0.7109686714,"remaining_time":0.2879873099},
{"learn":[0.2700335608],"iteration":712,"passed_time":0.7119117689,"remaining_time":0.2869644349},
{"learn":[0.2698791472],"iteration":713,"passed_time":0.7127996759,"remaining_time":0.2859196456},
{"learn":[0.2697183119],"iteration":714,"passed_time":0.7137143131,"remaining_time":0.2848859653},
{"learn":[0.2696207951],"iteration":715,"passed_time":0.7146030802,"remaining_time":0.2838423423},
{"learn":[0.2694437571],"iteration":716,"passed_time":0.715473517,"remaining_time":0.2827919069},
{"learn":[0.2691741943],"iteration":717,"passed_time":0.7163450339,"remaining_time":0.2817423983},
{"learn":[0.2689164583],"iteration":718,"passed_time":0.7172094708,"remaining_time":0.2806906146},
{"learn":[0.2687351458],"iteration":719,"passed_time":0.7183141595,"remaining_time":0.2797329133},
{"learn":[0.2684548148],"iteration":720,"passed_time":0.7192058665,"remaining_time":0.2786922733},
{"learn":[0.2683354272],"iteration":721,"passed_time":0.7212654628,"remaining_time":0.278102356},
{"learn":[0.268269019],"iteration":722,"passed_time":0.7230139767,"remaining_time":0.2773890187},
{"learn":[0.268122797],"iteration":723,"passed_time":0.724192286,"remaining_time":0.2764551465},
{"learn":[0.2680612934],"iteration":724,"passed_time":0.7251854238,"remaining_time":0.2754502646},
{"learn":[0.2678925718],"iteration":725,"passed_time":0.7261295013,"remaining_time":0.2744268736},
{"learn":[0.2677412084],"iteration":726,"passed_time":0.7275011721,"remaining_time":0.2735644903},
{"learn":[0.2675853849],"iteration":727,"passed_time":0.7290116641,"remaining_time":0.2727526446},
{"learn":[0.2673253452],"iteration":728,"passed_time":0.7299619116,"remaining_time":0.271730327},
{"learn":[0.2672069068],"iteration":729,"passed_time":0.7310886705,"remaining_time":0.2707735817},
{"learn":[0.2670559728],"iteration":730,"passed_time":0.7336131505,"remaining_time":0.2703314212},
{"learn":[0.2668664947],"iteration":731,"passed_time":0.7348022299,"remaining_time":0.2693939776},
{"learn":[0.2667146027],"iteration":732,"passed_time":0.7358572382,"remaining_time":0.2684069434},
{"learn":[0.266613007],"iteration":733,"passed_time":0.7367986756,"remaining_time":0.2673785099},
{"learn":[0.2664417566],"iteration":734,"passed_time":0.7377718033,"remaining_time":0.2663617546},
{"learn":[0.2663319443],"iteration":735,"passed_time":0.7387649612,"remaining_time":0.2653523126},
{"learn":[0.266122904],"iteration":736,"passed_time":0.7395761276,"remaining_time":0.2642778826},
{"learn":[0.2660275647],"iteration":737,"passed_time":0.7403368636,"remaining_time":0.2631862392},
{"learn":[0.2659465802],"iteration":738,"passed_time":0.74113948,"remaining_time":0.2621103039},
{"learn":[0.2658508751],"iteration":739,"passed_time":0.7418940259,"remaining_time":0.2610181959},
{"learn":[0.2657496844],"iteration":740,"passed_time":0.7430164148,"remaining_time":0.2600557452},
{"learn":[0.2655337175],"iteration":741,"passed_time":0.7439906425,"remaining_time":0.2590412763},
{"learn":[0.2654349988],"iteration":742,"passed_time":0.746835155,"remaining_time":0.25867471},
{"learn":[0.2653571858],"iteration":743,"passed_time":0.750121621,"remaining_time":0.2584537483},
{"learn":[0.2651441173],"iteration":744,"passed_time":0.7538554705,"remaining_time":0.258377883},
{"learn":[0.2648249162],"iteration":745,"passed_time":0.7548826286,"remaining_time":0.2573693794},
{"learn":[0.2647606474],"iteration":746,"passed_time":0.7557361754,"remaining_time":0.2563019469},
{"learn":[0.2646585673],"iteration":747,"passed_time":0.756578492,"remaining_time":0.2552312985},
{"learn":[0.2645243891],"iteration":748,"passed_time":0.757455919,"remaining_time":0.2541730423},
{"learn":[0.2643200415],"iteration":749,"passed_time":0.7583178758,"remaining_time":0.2531101054},
{"learn":[0.2642226736],"iteration":750,"passed_time":0.7593421339,"remaining_time":0.2521015885},
{"learn":[0.2641578454],"iteration":751,"passed_time":0.7608466358,"remaining_time":0.2512516187},
{"learn":[0.2638192147],"iteration":752,"passed_time":0.7616638322,"remaining_time":0.2501741577},
{"learn":[0.2635958495],"iteration":753,"passed_time":0.762385808,"remaining_time":0.2490662799},
{"learn":[0.2633208644],"iteration":754,"passed_time":0.7632849151,"remaining_time":0.2480169817},
{"learn":[0.2631834581],"iteration":755,"passed_time":0.7649141979,"remaining_time":0.2472040587},
{"learn":[0.262860884],"iteration":756,"passed_time":0.767202326,"remaining_time":0.2466007477},
{"learn":[0.2627260331],"iteration":757,"passed_time":0.7681352434,"remaining_time":0.2455597476},
{"learn":[0.2624091185],"iteration":758,"passed_time":0.7689279797,"remaining_time":0.2444744632},
{"learn":[0.2622163237],"iteration":759,"passed_time":0.7697061758,"remaining_time":0.243385352},
{"learn":[0.2620344413],"iteration":760,"passed_time":0.7705793027,"remaining_time":0.2423269123},
{"learn":[0.2618867925],"iteration":761,"passed_time":0.7713591789,"remaining_time":0.2412397958},
{"learn":[0.2616860466],"iteration":762,"passed_time":0.7720852046,"remaining_time":0.2401367369},
{"learn":[0.2615226036],"iteration":763,"passed_time":0.7728064703,"remaining_time":0.239033194},
{"learn":[0.2611454868],"iteration":764,"passed_time":0.7735619463,"remaining_time":0.2379411746},
{"learn":[0.261045383],"iteration":765,"passed_time":0.7744762036,"remaining_time":0.2368986034},
{"learn":[0.2609103739],"iteration":766,"passed_time":0.7753761107,"remaining_time":0.2358520023},
{"learn":[0.2608402585],"iteration":767,"passed_time":0.7764221089,"remaining_time":0.234849973},
{"learn":[0.2607813714],"iteration":768,"passed_time":0.7771746249,"remaining_time":0.2337595551},
{"learn":[0.2605709509],"iteration":769,"passed_time":0.7779642411,"remaining_time":0.2326811124},
{"learn":[0.2603960445],"iteration":770,"passed_time":0.7786921569,"remaining_time":0.23158507},
{"learn":[0.2603422543],"iteration":771,"passed_time":0.7794063325,"remaining_time":0.2304859193},
{"learn":[0.2601374283],"iteration":772,"passed_time":0.780483511,"remaining_time":0.2294945039},
{"learn":[0.2600726532],"iteration":773,"passed_time":0.7814794089,"remaining_time":0.2284791027},
{"learn":[0.2599420299],"iteration":774,"passed_time":0.7825408573,"remaining_time":0.2274828074},
{"learn":[0.2597540521],"iteration":775,"passed_time":0.7833367036,"remaining_time":0.2264095763},
{"learn":[0.2596306618],"iteration":776,"passed_time":0.7840720994,"remaining_time":0.2253196884},
{"learn":[0.2593989325],"iteration":777,"passed_time":0.7848303454,"remaining_time":0.2242372415},
{"learn":[0.259213059],"iteration":778,"passed_time":0.7855698013,"remaining_time":0.2231502906},
{"learn":[0.2591420645],"iteration":779,"passed_time":0.786300247,"remaining_time":0.2220616872},
{"learn":[0.2590682581],"iteration":780,"passed_time":0.7870223728,"remaining_time":0.2209716662},
{"learn":[0.2587762992],"iteration":781,"passed_time":0.7877877788,"remaining_time":0.2198946681},
{"learn":[0.2586922151],"iteration":782,"passed_time":0.7884870043,"remaining_time":0.2188001022},
{"learn":[0.2585693549],"iteration":783,"passed_time":0.7892334602,"remaining_time":0.2177195752},
{"learn":[0.258192158],"iteration":784,"passed_time":0.7902086779,"remaining_time":0.2167026349},
{"learn":[0.2579635184],"iteration":785,"passed_time":0.7909830141,"remaining_time":0.2156310382},
{"learn":[0.257828102],"iteration":786,"passed_time":0.7921902336,"remaining_time":0.2146775061},
{"learn":[0.2576680363],"iteration":787,"passed_time":0.7929419096,"remaining_time":0.213600616},
{"learn":[0.2575379705],"iteration":788,"passed_time":0.7936724953,"remaining_time":0.2125189042},
{"learn":[0.2574120656],"iteration":789,"passed_time":0.7944198212,"remaining_time":0.211442538},
{"learn":[0.2572851044],"iteration":790,"passed_time":0.7951597471,"remaining_time":0.210365047},
{"learn":[0.2569868173],"iteration":791,"passed_time":0.7960714843,"remaining_time":0.2093335888},
{"learn":[0.2567125438],"iteration":792,"passed_time":0.7969833115,"remaining_time":0.2083024564},
{"learn":[0.2565850343],"iteration":793,"passed_time":0.7977340074,"remaining_time":0.2072297674},
{"learn":[0.2563793136],"iteration":794,"passed_time":0.7984639032,"remaining_time":0.2061525191},
{"learn":[0.2562663731],"iteration":795,"passed_time":0.7991633087,"remaining_time":0.2050683207},
{"learn":[0.2561413864],"iteration":796,"passed_time":0.7998588742,"remaining_time":0.2039841099},
{"learn":[0.2560814681],"iteration":797,"passed_time":0.8005310296,"remaining_time":0.202894941},
{"learn":[0.2559354974],"iteration":798,"passed_time":0.8012026249,"remaining_time":0.2018066762},
{"learn":[0.2558710341],"iteration":799,"passed_time":0.8019087305,"remaining_time":0.2007280927},
{"learn":[0.2557080338],"iteration":800,"passed_time":0.8026212661,"remaining_time":0.1996520399},
{"learn":[0.2555639478],"iteration":801,"passed_time":0.8032817713,"remaining_time":0.1985640334},
{"learn":[0.2553143382],"iteration":802,"passed_time":0.8039777268,"remaining_time":0.1974858007},
{"learn":[0.2552124222],"iteration":803,"passed_time":0.8046590122,"remaining_time":0.1964049395},
{"learn":[0.2551083061],"iteration":804,"passed_time":0.8053838279,"remaining_time":0.1953356299},
{"learn":[0.2548969666],"iteration":805,"passed_time":0.8060771434,"remaining_time":0.1942595849},
{"learn":[0.2547636539],"iteration":806,"passed_time":0.806787499,"remaining_time":0.1931885699},
{"learn":[0.2546007308],"iteration":807,"passed_time":0.8074577743,"remaining_time":0.1921089129},
{"learn":[0.2545411703],"iteration":808,"passed_time":0.8081942001,"remaining_time":0.1910459062},
{"learn":[0.2544309321],"iteration":809,"passed_time":0.8088588254,"remaining_time":0.189966844},
{"learn":[0.2542851027],"iteration":810,"passed_time":0.8095529709,"remaining_time":0.1888956932},
{"learn":[0.2541500227],"iteration":811,"passed_time":0.8104363179,"remaining_time":0.1878693314},
{"learn":[0.2540655987],"iteration":812,"passed_time":0.8116395074,"remaining_time":0.1869169802},
{"learn":[0.2539201404],"iteration":813,"passed_time":0.8123642731,"remaining_time":0.185854557},
{"learn":[0.2537730646],"iteration":814,"passed_time":0.8131613094,"remaining_time":0.1848093885},
{"learn":[0.2535819537],"iteration":815,"passed_time":0.8139553257,"remaining_time":0.1837641472},
{"learn":[0.2533954955],"iteration":816,"passed_time":0.8147002716,"remaining_time":0.1827085168},
{"learn":[0.2532931174],"iteration":817,"passed_time":0.8154668877,"remaining_time":0.1816584744},
{"learn":[0.2531429437],"iteration":818,"passed_time":0.8162330737,"remaining_time":0.1806090298},
{"learn":[0.252986117],"iteration":819,"passed_time":0.8171037406,"remaining_time":0.1795832397},
{"learn":[0.2527446191],"iteration":820,"passed_time":0.8178507965,"remaining_time":0.1785308446},
{"learn":[0.252463015],"iteration":821,"passed_time":0.8186179526,"remaining_time":0.1774835512},
{"learn":[0.2522998561],"iteration":822,"passed_time":0.8194002788,"remaining_time":0.176440206},
{"learn":[0.252071464],"iteration":823,"passed_time":0.8201744549,"remaining_time":0.1753957522},
{"learn":[0.251984846],"iteration":824,"passed_time":0.8209966214,"remaining_time":0.1743621465},
{"learn":[0.2518931239],"iteration":825,"passed_time":0.8218231679,"remaining_time":0.1733299772},
{"learn":[0.2518166514],"iteration":826,"passed_time":0.8225624438,"remaining_time":0.1722800276},
{"learn":[0.2514718662],"iteration":827,"passed_time":0.8233382599,"remaining_time":0.1712384289},
{"learn":[0.2513989216],"iteration":828,"passed_time":0.8250804637,"remaining_time":0.1703970523},
{"learn":[0.2512396438],"iteration":829,"passed_time":0.8262325928,"remaining_time":0.1694324979},
{"learn":[0.2511046966],"iteration":830,"passed_time":0.8272421308,"remaining_time":0.1684384579},
{"learn":[0.2508916764],"iteration":831,"passed_time":0.8282978891,"remaining_time":0.1674537249},
{"learn":[0.2507478227],"iteration":832,"passed_time":0.8292875169,"remaining_time":0.1664555473},
{"learn":[0.2506923776],"iteration":833,"passed_time":0.8302339644,"remaining_time":0.1654487852},
{"learn":[0.2505960145],"iteration":834,"passed_time":0.8311812919,"remaining_time":0.1644423419},
{"learn":[0.2504475659],"iteration":835,"passed_time":0.8321810298,"remaining_time":0.163446334},
{"learn":[0.2502756069],"iteration":836,"passed_time":0.8337480222,"remaining_time":0.1625609182},
{"learn":[0.2502399888],"iteration":837,"passed_time":0.8347180899,"remaining_time":0.16155834},
{"learn":[0.2501054958],"iteration":838,"passed_time":0.8355845567,"remaining_time":0.1605359351},
{"learn":[0.2499462525],"iteration":839,"passed_time":0.8365785346,"remaining_time":0.1595382188},
{"learn":[0.2498124303],"iteration":840,"passed_time":0.8374003611,"remaining_time":0.1585079255},
{"learn":[0.2496781205],"iteration":841,"passed_time":0.8382024474,"remaining_time":0.1574744194},
{"learn":[0.2494698614],"iteration":842,"passed_time":0.8389733235,"remaining_time":0.1564356435},
{"learn":[0.249330489],"iteration":843,"passed_time":0.8397205894,"remaining_time":0.155393134},
{"learn":[0.2491070481],"iteration":844,"passed_time":0.8404564952,"remaining_time":0.1543492379},
{"learn":[0.2489377749],"iteration":845,"passed_time":0.8412280513,"remaining_time":0.1533125679},
{"learn":[0.2486522422],"iteration":846,"passed_time":0.8427826936,"remaining_time":0.1524181467},
{"learn":[0.2484338458],"iteration":847,"passed_time":0.84358308,"remaining_time":0.1513868101},
{"learn":[0.2481833122],"iteration":848,"passed_time":0.8443256758,"remaining_time":0.1503457277},
{"learn":[0.2479636655],"iteration":849,"passed_time":0.8450903419,"remaining_time":0.1493092477},
{"learn":[0.2478911113],"iteration":850,"passed_time":0.8458331777,"remaining_time":0.1482695806},
{"learn":[0.2478196024],"iteration":851,"passed_time":0.8465502034,"remaining_time":0.1472261223},
{"learn":[0.2476042126],"iteration":852,"passed_time":0.8472819292,"remaining_time":0.1461859667},
{"learn":[0.247481935],"iteration":853,"passed_time":0.848012975,"remaining_time":0.1451464178},
{"learn":[0.2473940057],"iteration":854,"passed_time":0.848768281,"remaining_time":0.1441117105},
{"learn":[0.2471769956],"iteration":855,"passed_time":0.8494861266,"remaining_time":0.1430713476},
{"learn":[0.2470145237],"iteration":856,"passed_time":0.8502068523,"remaining_time":0.1420322195},
{"learn":[0.2468828789],"iteration":857,"passed_time":0.8509644683,"remaining_time":0.1409999469},
{"learn":[0.2466969952],"iteration":858,"passed_time":0.8517047642,"remaining_time":0.1399654682},
{"learn":[0.2465036918],"iteration":859,"passed_time":0.852574191,"remaining_time":0.1389527203},
{"learn":[0.2463509766],"iteration":860,"passed_time":0.853327107,"remaining_time":0.1379214743},
{"learn":[0.2461975583],"iteration":861,"passed_time":0.8540559728,"remaining_time":0.13688702},
{"learn":[0.2460844458],"iteration":862,"passed_time":0.8547709384,"remaining_time":0.1358510656},
{"learn":[0.2459913706],"iteration":863,"passed_time":0.8555040042,"remaining_time":0.1348187075},
{"learn":[0.2458476458],"iteration":864,"passed_time":0.8562850404,"remaining_time":0.1337945376},
{"learn":[0.2457531705],"iteration":865,"passed_time":0.8570749766,"remaining_time":0.1327723085},
{"learn":[0.2456090884],"iteration":866,"passed_time":0.8578693629,"remaining_time":0.1317512994},
{"learn":[0.2455383223],"iteration":867,"passed_time":0.8592316637,"remaining_time":0.1308172775},
{"learn":[0.2453649341],"iteration":868,"passed_time":0.8600649303,"remaining_time":0.1298024261},
{"learn":[0.2452740434],"iteration":869,"passed_time":0.8608331364,"remaining_time":0.1287782598},
{"learn":[0.2451689488],"iteration":870,"passed_time":0.8615871523,"remaining_time":0.1277525778},
{"learn":[0.2449340131],"iteration":871,"passed_time":0.8623877086,"remaining_time":0.126734359},
{"learn":[0.2448479604],"iteration":872,"passed_time":0.8631274345,"remaining_time":0.12570778},
{"learn":[0.2446773095],"iteration":873,"passed_time":0.8638887305,"remaining_time":0.1246849714},
{"learn":[0.2445161467],"iteration":874,"passed_time":0.8646341864,"remaining_time":0.1236604958},
{"learn":[0.2444499701],"iteration":875,"passed_time":0.865345792,"remaining_time":0.1226318608},
{"learn":[0.2442882552],"iteration":876,"passed_time":0.8660831579,"remaining_time":0.1216075667},
{"learn":[0.2441670201],"iteration":877,"passed_time":0.8668477039,"remaining_time":0.120587708},
{"learn":[0.2440473031],"iteration":878,"passed_time":0.8675516995,"remaining_time":0.1195600861},
{"learn":[0.2438668358],"iteration":879,"passed_time":0.8684700967,"remaining_time":0.1185624705},
{"learn":[0.2438084969],"iteration":880,"passed_time":0.8691949025,"remaining_time":0.1175388561},
{"learn":[0.2435897119],"iteration":881,"passed_time":0.8698812179,"remaining_time":0.1165107647},
{"learn":[0.243510513],"iteration":882,"passed_time":0.8705651133,"remaining_time":0.1154831273},
{"learn":[0.2434718071],"iteration":883,"passed_time":0.8732102342,"remaining_time":0.1147139153},
{"learn":[0.243377432],"iteration":884,"passed_time":0.8744690542,"remaining_time":0.1137601145},
{"learn":[0.2431867234],"iteration":885,"passed_time":0.8752792006,"remaining_time":0.1127478292},
{"learn":[0.2430820992],"iteration":886,"passed_time":0.8760293265,"remaining_time":0.1117283453},
{"learn":[0.2427630968],"iteration":887,"passed_time":0.8767878625,"remaining_time":0.1107105306},
{"learn":[0.2426863772],"iteration":888,"passed_time":0.8775073782,"remaining_time":0.1096884223},
{"learn":[0.2425753914],"iteration":889,"passed_time":0.8782352539,"remaining_time":0.1086680292},
{"learn":[0.2424409553],"iteration":890,"passed_time":0.8789639097,"remaining_time":0.1076483889},
{"learn":[0.242267971],"iteration":891,"passed_time":0.8796880554,"remaining_time":0.1066288552},
{"learn":[0.2420777066],"iteration":892,"passed_time":0.8804140912,"remaining_time":0.1056102105},
{"learn":[0.2419898002],"iteration":893,"passed_time":0.8811623171,"remaining_time":0.1045948551},
{"learn":[0.2418552332],"iteration":894,"passed_time":0.881913003,"remaining_time":0.1035803863},
{"learn":[0.2417564112],"iteration":895,"passed_time":0.8826455388,"remaining_time":0.1025643978},
{"learn":[0.2416265825],"iteration":896,"passed_time":0.883681447,"remaining_time":0.1015839163},
{"learn":[0.2414420451],"iteration":897,"passed_time":0.8844475431,"remaining_time":0.1005726303},
{"learn":[0.241257755],"iteration":898,"passed_time":0.8851766788,"remaining_time":0.09955773336},
{"learn":[0.241165407],"iteration":899,"passed_time":0.8859040546,"remaining_time":0.09854327637},
{"learn":[0.2410883758],"iteration":900,"passed_time":0.8866343304,"remaining_time":0.09752977634},
{"learn":[0.240946318],"iteration":901,"passed_time":0.8873699562,"remaining_time":0.09651748691},
{"learn":[0.2408603529],"iteration":902,"passed_time":0.888110872,"remaining_time":0.09550637981},
{"learn":[0.2407733235],"iteration":903,"passed_time":0.8888355478,"remaining_time":0.09449414461},
{"learn":[0.2406745329],"iteration":904,"passed_time":0.8895814137,"remaining_time":0.09348477245},
{"learn":[0.2405418369],"iteration":905,"passed_time":0.8903067794,"remaining_time":0.09247385333},
{"learn":[0.2404203767],"iteration":906,"passed_time":0.8910349051,"remaining_time":0.09146384788},
{"learn":[0.2403723244],"iteration":907,"passed_time":0.891772011,"remaining_time":0.09045537487},
{"learn":[0.2402364579],"iteration":908,"passed_time":0.8937270464,"remaining_time":0.08956956082},
{"learn":[0.2400634234],"iteration":909,"passed_time":0.8948599554,"remaining_time":0.08859999558},
{"learn":[0.2398301305],"iteration":910,"passed_time":0.8968756513,"remaining_time":0.08771640986},
{"learn":[0.2397401147],"iteration":911,"passed_time":0.9015560283,"remaining_time":0.08708773929},
{"learn":[0.2395971788],"iteration":912,"passed_time":0.9038283863,"remaining_time":0.08622047106},
{"learn":[0.2394459808],"iteration":913,"passed_time":0.9094629909,"remaining_time":0.08566683156},
{"learn":[0.2393618655],"iteration":914,"passed_time":0.9107949714,"remaining_time":0.08470193935},
{"learn":[0.2393168468],"iteration":915,"passed_time":0.9123123334,"remaining_time":0.08375326339},
{"learn":[0.2392354431],"iteration":916,"passed_time":0.9140145368,"remaining_time":0.0828200945},
{"learn":[0.2391601505],"iteration":917,"passed_time":0.9149057339,"remaining_time":0.08181272648},
{"learn":[0.2389633857],"iteration":918,"passed_time":0.9157294204,"remaining_time":0.08079965474},
{"learn":[0.2388245119],"iteration":919,"passed_time":0.9186147332,"remaining_time":0.07996646209},
{"learn":[0.2386163953],"iteration":920,"passed_time":0.9200513846,"remaining_time":0.07900441237},
{"learn":[0.2385557937],"iteration":921,"passed_time":0.9218631089,"remaining_time":0.07807309717},
{"learn":[0.2384032166],"iteration":922,"passed_time":0.9228779369,"remaining_time":0.07707332011},
{"learn":[0.2382553393],"iteration":923,"passed_time":0.9237900941,"remaining_time":0.0760650565},
{"learn":[0.2381469778],"iteration":924,"passed_time":0.9249800335,"remaining_time":0.07507954818},
{"learn":[0.2380847217],"iteration":925,"passed_time":0.9263195841,"remaining_time":0.07410556673},
{"learn":[0.2379183844],"iteration":926,"passed_time":0.9272774417,"remaining_time":0.07310070545},
{"learn":[0.2378718464],"iteration":927,"passed_time":0.9280181276,"remaining_time":0.07207907787},
{"learn":[0.2377020113],"iteration":928,"passed_time":0.9289113246,"remaining_time":0.07106972419},
{"learn":[0.2375929526],"iteration":929,"passed_time":0.9297484812,"remaining_time":0.07005639794},
{"learn":[0.2373326779],"iteration":930,"passed_time":0.9309047704,"remaining_time":0.06906712813},
{"learn":[0.2372308308],"iteration":931,"passed_time":0.9316656464,"remaining_time":0.06804861864},
{"learn":[0.2371223318],"iteration":932,"passed_time":0.9325140931,"remaining_time":0.06703695734},
{"learn":[0.2369850857],"iteration":933,"passed_time":0.9334544605,"remaining_time":0.06603214833},
{"learn":[0.2368431293],"iteration":934,"passed_time":0.9343483276,"remaining_time":0.06502424122},
{"learn":[0.2367220866],"iteration":935,"passed_time":0.935160744,"remaining_time":0.0640110028},
{"learn":[0.2366153061],"iteration":936,"passed_time":0.9361262717,"remaining_time":0.06300849905},
{"learn":[0.2365678835],"iteration":937,"passed_time":0.9370079586,"remaining_time":0.06200052661},
{"learn":[0.2365237592],"iteration":938,"passed_time":0.9378283251,"remaining_time":0.06098883564},
{"learn":[0.2364763046],"iteration":939,"passed_time":0.9386031113,"remaining_time":0.0599746397},
{"learn":[0.2363225411],"iteration":940,"passed_time":0.9393826574,"remaining_time":0.0589612519},
{"learn":[0.2362133752],"iteration":941,"passed_time":0.9403929254,"remaining_time":0.05796258201},
{"learn":[0.2361081878],"iteration":942,"passed_time":0.9412053718,"remaining_time":0.0569519174},
{"learn":[0.2359727394],"iteration":943,"passed_time":0.9419663078,"remaining_time":0.05593861425},
{"learn":[0.2358317009],"iteration":944,"passed_time":0.9427357239,"remaining_time":0.05492633985},
{"learn":[0.2356715357],"iteration":945,"passed_time":0.9435178801,"remaining_time":0.05391530744},
{"learn":[0.2355300865],"iteration":946,"passed_time":0.9443198565,"remaining_time":0.05290586934},
{"learn":[0.2354333567],"iteration":947,"passed_time":0.9452328937,"remaining_time":0.05190296776},
{"learn":[0.2353605644],"iteration":948,"passed_time":0.9460191299,"remaining_time":0.0508934342},
{"learn":[0.2352307027],"iteration":949,"passed_time":0.9468065661,"remaining_time":0.04988443446},
{"learn":[0.2349890606],"iteration":950,"passed_time":0.9475838823,"remaining_time":0.04887537919},
{"learn":[0.234880462],"iteration":951,"passed_time":0.9483864186,"remaining_time":0.04786808422},
{"learn":[0.2348331451],"iteration":952,"passed_time":0.949200845,"remaining_time":0.04686180643},
{"learn":[0.2347648479],"iteration":953,"passed_time":0.9499758312,"remaining_time":0.04585402753},
{"learn":[0.2345714385],"iteration":954,"passed_time":0.9507754575,"remaining_time":0.04484789894},
{"learn":[0.2344630673],"iteration":955,"passed_time":0.9516853647,"remaining_time":0.04384728382},
{"learn":[0.2343773031],"iteration":956,"passed_time":0.9525316714,"remaining_time":0.04284399777},
{"learn":[0.234301934],"iteration":957,"passed_time":0.9547751491,"remaining_time":0.04190235764},
{"learn":[0.2341956319],"iteration":958,"passed_time":0.9560533092,"remaining_time":0.04091668651},
{"learn":[0.2340432441],"iteration":959,"passed_time":0.9567581048,"remaining_time":0.03990649029},
{"learn":[0.2339805319],"iteration":960,"passed_time":0.9574426202,"remaining_time":0.03889610645},
{"learn":[0.233871895],"iteration":961,"passed_time":0.9581564859,"remaining_time":0.03788756136},
{"learn":[0.2337968189],"iteration":962,"passed_time":0.9591010033,"remaining_time":0.03688850013},
{"learn":[0.2337110533],"iteration":963,"passed_time":0.9629723839,"remaining_time":0.03599896762},
{"learn":[0.2335670974],"iteration":964,"passed_time":0.9641632034,"remaining_time":0.03500592543},
{"learn":[0.2334285956],"iteration":965,"passed_time":0.9651159509,"remaining_time":0.03400408532},
{"learn":[0.2331068397],"iteration":966,"passed_time":0.966138349,"remaining_time":0.03300472621},
{"learn":[0.2328930927],"iteration":967,"passed_time":0.9680564041,"remaining_time":0.03203495856},
{"learn":[0.2327941425],"iteration":968,"passed_time":0.9693459743,"remaining_time":0.03104310455},
{"learn":[0.2325842835],"iteration":969,"passed_time":0.9704041727,"remaining_time":0.03004347284},
{"learn":[0.232450066],"iteration":970,"passed_time":0.97133134,"remaining_time":0.02903980295},
{"learn":[0.2322932603],"iteration":971,"passed_time":0.9722494673,"remaining_time":0.02803602995},
{"learn":[0.2320537186],"iteration":972,"passed_time":0.9731522244,"remaining_time":0.02703200623},
{"learn":[0.2319185729],"iteration":973,"passed_time":0.9740230813,"remaining_time":0.02602733825},
{"learn":[0.2318803525],"iteration":974,"passed_time":0.9748802881,"remaining_time":0.02502259466},
{"learn":[0.2315760738],"iteration":975,"passed_time":0.9757667751,"remaining_time":0.02401887446},
{"learn":[0.2314845078],"iteration":976,"passed_time":0.9767272227,"remaining_time":0.02301713742},
{"learn":[0.2313599153],"iteration":977,"passed_time":0.9777944211,"remaining_time":0.02201788871},
{"learn":[0.2312427785],"iteration":978,"passed_time":0.9786733481,"remaining_time":0.02101445839},
{"learn":[0.2311188463],"iteration":979,"passed_time":0.9796913261,"remaining_time":0.02001412311},
{"learn":[0.2310521856],"iteration":980,"passed_time":0.9805346428,"remaining_time":0.01901036552},
{"learn":[0.2309828552],"iteration":981,"passed_time":0.9813944096,"remaining_time":0.01800723687},
{"learn":[0.2309092566],"iteration":982,"passed_time":0.9823410471,"remaining_time":0.01700590407},
{"learn":[0.2307509372],"iteration":983,"passed_time":0.9831952538,"remaining_time":0.01600317809},
{"learn":[0.2306278087],"iteration":984,"passed_time":0.984105351,"remaining_time":0.01500160596},
{"learn":[0.2305408791],"iteration":985,"passed_time":0.9862315678,"remaining_time":0.01401750452},
{"learn":[0.2303903417],"iteration":986,"passed_time":0.9870531643,"remaining_time":0.01301388553},
{"learn":[0.2303360117],"iteration":987,"passed_time":0.9878194404,"remaining_time":0.0120099628},
{"learn":[0.2300579294],"iteration":988,"passed_time":0.9885051758,"remaining_time":0.01100562443},
{"learn":[0.23000792],"iteration":989,"passed_time":0.9891929313,"remaining_time":0.01000195077},
{"learn":[0.2297048056],"iteration":990,"passed_time":0.9898777567,"remaining_time":0.008998888697},
{"learn":[0.2296497452],"iteration":991,"passed_time":0.9906205525,"remaining_time":0.007996936852},
{"learn":[0.2295957393],"iteration":992,"passed_time":0.9913311482,"remaining_time":0.006995280279},
{"learn":[0.2294958912],"iteration":993,"passed_time":0.9920304237,"remaining_time":0.005994141533},
{"learn":[0.2294008865],"iteration":994,"passed_time":0.9927695495,"remaining_time":0.004993810611},
{"learn":[0.2292646432],"iteration":995,"passed_time":0.9936075562,"remaining_time":0.003994402236},
{"learn":[0.2291856609],"iteration":996,"passed_time":0.9944249426,"remaining_time":0.002995255851},
{"learn":[0.2291183667],"iteration":997,"passed_time":0.9953275698,"remaining_time":0.001996645075},
{"learn":[0.229067324],"iteration":998,"passed_time":0.9960952758,"remaining_time":0.0009980914587},
{"learn":[0.228910952],"iteration":999,"passed_time":0.9968671619,"remaining_time":0}
]}